{
  "m_GameObject": {
    "m_FileID": 0,
    "m_PathID": 0
  },
  "m_Enabled": 1,
  "m_Script": {
    "m_FileID": 0,
    "m_PathID": -1707786903170945384
  },
  "m_Name": "EP02_13",
  "Path": "Assets/AddressableAssets/Lua/Scenario/EP02/EP02_13.lua",
  "Text": "function EP02_13()\r\n    --.承-7【5月第2週】「どきどき☆お着替えチャンス」\r\n    SaveData.Title = \"どきどき☆お着替えチャンス\"\r\n\r\n    --//BG：1-A教室\r\n    LAYER_LOAD(LAYER_BG, \"BG014aa\")\r\n    SWITCH_SCREEN(\"mask000\" , 1000,false)\r\n\r\n    --//SE：騒ぐ声\r\n--PLAY_SE(\"SEf003.wav\")\r\n\r\n    --//CG：着替えるクラスメイトに囲まれるエリカ。\r\n    LAYER_LOAD(LAYER_BG, \"EV010aa\")\r\n    SWITCH_SCREEN(\"mask000\" , 1000)\r\n\r\n    --//effectフォント大\r\n    -- wiz : 要検討\r\n    MSG([[ I’m… in big troubleーーーーーーーーー!!!! ]])\r\n\r\n    MSG([[ The story goes back ten minutes―― ]])\r\n\r\n    LAYER_LOAD(LAYER_BG,\"BG000aa\")\r\n    SWITCH_SCREEN(\"mask015\",1000,false)\r\n    WAIT_INPUT(1000)\r\n\r\n    --//BG：1F廊下\r\n    LAYER_LOAD(LAYER_BG, \"BG013aa\")\r\n    --//BU：モブ女性\r\n    LAYER_LOAD(50,\"BU_MOB02aa\")\r\n    SWITCH_SCREEN(\"mask015\" , 1000,false)\r\n\r\nPLAY_BGM(\"BGM02.wav\")\r\n\r\nPLAY_VOICE(\"itoh_0020.wav\")\r\n    MSG([[\r\n    【Mr. Ito】\r\n “Erika, I’m sorry to have you carry the prints to the staff room. But since you’re a ‘Princess’ candidate, you should leave this kind of thing to the ‘Knights.” ]])\r\n\r\nLAYER_LOAD_FACE(\"BU_ERI01fa\")\r\nPLAY_VOICE(\"erika_0248.wav\")\r\n    MSG([[\r\n    【Erika】wry smile\r\n “No, I’m the day’s monitor today. The Knights usually support me, so I want to handle the small chores myself.” ]])\r\nLAYER_LOAD_FACE(\"\")\r\n\r\nPLAY_VOICE(\"itoh_0021.wav\")\r\n    MSG([[\r\n    【Mr. Ito】\r\n “Hehe, I think you’d make a good ‘Princess.’ Do your best.” ]])\r\n\r\n    SWITCH_SCREEN(\"mask000\",0,false)\r\n    LAYER_MOVE_ALPHA(50,0,500,Ease.Liner)\r\n    LAYER_MOVE_POSITION(50,-200,0,500,Ease.InSine)\r\n    WAIT(500)\r\n    LAYER_LOAD(50,\"\")\r\n\r\n    MSG([[ After delivering the prints to the teacher’s desk, I left the staff room. ]])\r\n\r\n    MSG([[ Alright, time to head back to class. ]])\r\n\r\n    MSG([[ What was the next class again? Yuriai Private Academy has two weekly schedules—A week and B week—with different lesson structures, so my memory is still a bit fuzzy. ]])\r\n\r\n    MSG([[ I brought all the textbooks I might need for either schedule, so I should be fine, but I’ll check as soon as I get back. ]])\r\n\r\n    LAYER_LOAD(LAYER_BG,\"BG000aa\")\r\n    SWITCH_SCREEN(\"mask001\",1000,false)\r\n\r\n    --//BG：4F廊下\r\n    LAYER_LOAD(LAYER_BG, \"BG013ad\")\r\n    SWITCH_SCREEN(\"mask001\" , 1000,false)\r\n\r\n    PLAY_SE(\"SEa017.wav\")\r\n    MSG([[ As I reached the fourth floor, I saw Hiyu running down the hallway. ]])\r\n\r\n    --WAIT(600)\r\n    --//BU：ヒユ（焦り）\r\n    LAYER_LOAD(50,\"BU_HIY01ga\")\r\n    LAYER_POSITION(50,-200,0)\r\n    LAYER_MOVE_POSITION(50,0,0,500,Ease.OutCubic)\r\n    SWITCH_SCREEN(\"mask000\",500,false)\r\n    STOP_SE(\"SEa017.wav\",500)\r\n\r\nPLAY_VOICE(\"hiyu_0121.wav\")\r\n    MSG([[\r\n    【Hiyu】frantic\r\n “E-Erika Onee-samaーーーーーー!!!” ]])\r\n\r\nLAYER_LOAD_FACE(\"BU_ERI01ca\")\r\nPLAY_VOICE(\"erika_0249.wav\")\r\n    MSG([[\r\n    【Erika】surprised\r\n “Hiyu? What’s wrong? You shouldn’t be running in the hallway.” ]])\r\nLAYER_LOAD_FACE(\"\")\r\n\r\n    LAYER_LOAD(50,\"BU_HIY01da\")\r\n    SWITCH_SCREEN(\"mask000\",300,true)\r\n\r\nPLAY_VOICE(\"hiyu_0122.wav\")\r\n    MSG([[\r\n    【Hiyu】sad\r\n “Hyuwah!? I-I'm sorry…” ]])\r\n\r\n    LAYER_LOAD(50,\"BU_HIY01ga\")\r\n    SWITCH_SCREEN(\"mask000\",300,true)\r\n\r\nPLAY_VOICE(\"hiyu_0123.wav\")\r\n    MSG([[\r\n    【Hiyu】frantic\r\n “But it’s not just that! The gym uniforms for the next class just arrived, so I need to change immediately!” ]])\r\n\r\nLAYER_LOAD_FACE(\"BU_ERI01ga\")\r\nPLAY_VOICE(\"erika_0250.wav\")\r\n    MSG([[\r\n    【Erika】frantic\r\n “G-Gym uniform?” ]])\r\nLAYER_LOAD_FACE(\"\")\r\n\r\nPLAY_VOICE(\"hiyu_0124.wav\")\r\n    MSG([[\r\n    【Hiyu】frantic\r\n “Yes! If I don’t change quickly, I’ll be late for class!” ]])\r\n\r\n    MSG([[ Of course, next up is P.E. ]])\r\n\r\n    MSG([[ Because the gym uniforms are custom-made, the classes had been doing simple recreation until everyone’s uniforms were ready. But I never thought they’d arrive today... ]])\r\n\r\n    MSG([[ Apparently, the reason for the custom order is an incident where a large number were auctioned off in the past. ]])\r\n\r\n    MSG([[ At a prestigious school like Yuriai Private Academy, even gym uniforms are premium items. How scary. ]])\r\n\r\nLAYER_LOAD_FACE(\"BU_ERI01da\")\r\nPLAY_VOICE(\"erika_0251.wav\")\r\n    MSG([[\r\n    【Erika】sad\r\n (W-What am I going to do about changing...) ]])\r\nLAYER_LOAD_FACE(\"\")\r\n\r\n    MSG([[ Yuriai Private Academy doesn’t have changing rooms. Since there are no boys, it’s tradition to close curtains and change in the classroom. ]])\r\n\r\n    MSG([[ So right now, the classroom is full of classmates who are changing. ]])\r\n\r\n    MSG([[ Even if I find somewhere to change alone, I can’t enter the classroom to get my gym uniform. ]])\r\n\r\n    MSG([[ ...I’m stuck. ]])\r\n\r\nLAYER_LOAD_FACE(\"BU_ERI01da\")\r\nPLAY_VOICE(\"erika_0252.wav\")\r\n    MSG([[\r\n    【Erika】sad\r\n (From now on, I’ll wear it under my uniform in advance… t-today I guess I have no choice but to feign illness and skip class) ]])\r\nLAYER_LOAD_FACE(\"\")\r\n\r\n    --//BU：ヒユ（焦り）、体操服リラ（驚き）、モブ体操服生徒Ｅ\r\n    --LAYER_LOAD(50,\"BU_HIY01ga\")\r\n    LAYER_LOAD(50,\"\")\r\n    LAYER_LOAD(LAYER_BG,\"BG013ah\")\r\n    LAYER_POSITION(LAYER_BG,500,-200)\r\n    SWITCH_SCREEN(\"mask000\",1000,false)\r\n\r\n    LAYER_LOAD(55,\"BUL_MOB08aa\")\r\n    LAYER_LOAD(60,\"BUL_RIR04ca\")\r\n    LAYER_POSITION(55,-700,0)\r\n    LAYER_POSITION(60,-300,0)\r\n    LAYER_MOVE_POSITION(55,-400,0,500,Ease.OutSine)\r\n    LAYER_MOVE_POSITION(60,0,0,500,Ease.OutSine)\r\n    SWITCH_SCREEN(\"mask000\",500,false)\r\n\r\nPLAY_VOICE(\"lira_0082.wav\")\r\n    MSG([[\r\n    【Lira】gym uniform・surprised\r\n “Huh? Erika, you haven’t changed yet?” ]])\r\n\r\nLAYER_LOAD_FACE(\"BU_ERI01ca\")\r\nPLAY_VOICE(\"erika_0253.wav\")\r\n    MSG([[\r\n    【Erika】surprised\r\n “L-Lira-san.” ]])\r\nLAYER_LOAD_FACE(\"\")\r\n\r\n    MSG([[ Lira arrived leading the Knights. Since the P.E. class is combined with Lira’s 1-B, everyone is in gym uniforms. ]])\r\n\r\nPLAY_VOICE(\"lira-knight_0001.wav\")\r\n    MSG([[\r\n    【Class 1-B students】\r\n “Hoo! Hoo!” ]])\r\n\r\n    MSG([[ And for some reason, they’re seriously fired up. W-What’s going on? ]])\r\n\r\n    LAYER_LOAD(60,\"BUL_RIR04aa\")\r\n    SWITCH_SCREEN(\"mask000\",300,true)\r\n\r\nPLAY_VOICE(\"lira_0083.wav\")\r\n    MSG([[\r\n    【Lira】normal\r\n “Hurry up and change. Let’s settle which class is better at P.E.—me or Erika.” ]])\r\n\r\n    LAYER_LOAD(60,\"BUL_RIR04ia\")\r\n    SWITCH_SCREEN(\"mask000\",300,true)\r\n\r\nPLAY_VOICE(\"lira_0084.wav\")\r\n    MSG([[\r\n    【Lira】wink\r\n “Though I doubt that bunch of weeds in Class A stands a chance. I might just pluck a few off<sprite=\"Emoji\" name=\"note\">” ]])\r\n\r\n    LAYER_LOAD(LAYER_BG,\"BG013ad\")\r\n    LAYER_LOAD(50,\"BU_HIY01ba\")\r\n    LAYER_POSITION(50,600,0)\r\n    LAYER_LOAD(60,\"BU_RIR04ia\")\r\n    LAYER_LOAD(55,\"BU_MOB08aa\")\r\n    LAYER_POSITION(55,-600,0)\r\n    SWITCH_SCREEN(\"mask000\",1000,false)\r\n\r\nPLAY_VOICE(\"hiyu_0125.wav\")\r\n    MSG([[\r\n    【Hiyu】serious\r\n “W-What did you sayーーー! I won’t tolerate anyone belittling Erika Onee-sama, even indirectly!” ]])\r\n\r\nPLAY_VOICE(\"hiyu_0126.wav\")\r\n    MSG([[\r\n    【Hiyu】serious\r\n “No way a flashy gal worrying only about fashion can beat a Battle Princess who repels perverts!” ]])\r\n\r\nPLAY_VOICE(\"lira-knight_0002.wav\")\r\n    MSG([[\r\n    【Class 1-B students】\r\n “Huh? Don’t underestimate gals! Princess Lira is serious about sports too!” ]])\r\n\r\n    MSG([[ Hiyu instantly bites at Lira’s taunt. 1-B class is annoyed by this. ]])\r\n\r\n    MSG([[ —Wait, this development, no way. I had a terrible premonition and tried to stop Hiyu. ]])\r\n\r\nLAYER_LOAD_FACE(\"BU_ERI01ga\")\r\nPLAY_VOICE(\"erika_0254.wav\")\r\n    MSG([[\r\n    【Erika】frantic\r\n “C-Calm down, Hiyu. There’s no need to compete in P.E., and I was thinking of skipping today’s class—” ]])\r\nLAYER_LOAD_FACE(\"\")\r\n\r\n    LAYER_LOAD(50,\"BU_HIY01ea\")\r\n    LAYER_POSITION(50,600,0)\r\n    SWITCH_SCREEN(\"mask000\",300,true)\r\n\r\nPLAY_VOICE(\"hiyu_0127.wav\")\r\n    MSG([[\r\n    【Hiyu】smile\r\n “So merciful even to your enemies, like a saint... Onee-sama, you truly are an angel. But don’t worry.” ]])\r\n\r\n    LAYER_LOAD(50,\"BU_HIY01ba\")\r\n    LAYER_POSITION(50,600,0)\r\n    SWITCH_SCREEN(\"mask000\",300,true)\r\n\r\nPLAY_VOICE(\"hiyu_0128.wav\")\r\n    MSG([[\r\n    【Hiyu】serious\r\n “We ‘Knights’ will defeat those gals and prove that Erika Onee-sama is supreme!” ]])\r\n\r\nLAYER_LOAD_FACE(\"BU_ERI01ga\")\r\nPLAY_VOICE(\"erika_0255.wav\")\r\n    MSG([[\r\n    【Erika】frantic\r\n “N-No, I was going to skip class—” ]])\r\nLAYER_LOAD_FACE(\"\")\r\n\r\nPLAY_VOICE(\"hiyu_0129.wav\")\r\n    MSG([[\r\n    【Hiyu】serious\r\n “I’ll change immediately, so Class 1-B, you better prepare yourselves!?” ]])\r\n\r\n    LAYER_LOAD(60,\"BU_RIR04ea\")\r\n    SWITCH_SCREEN(\"mask000\",300,true)\r\n\r\nPLAY_VOICE(\"lira_0085.wav\")\r\n    MSG([[\r\n    【Lira】smile\r\n “You better prepare carefully too. You’ll all have your necks neatly snipped<sprite=\"Emoji\" name=\"note\">” ]])\r\n\r\nPLAY_VOICE(\"lira-knight_0003.wav\")\r\n    MSG([[\r\n    【Class 1-B students】\r\n “We’ll win! For Princess Lira, we absolutely will!” ]])\r\n\r\nPLAY_VOICE(\"hiyu_0130.wav\")\r\n    MSG([[\r\n    【Hiyu】serious\r\n “Let’s go, Erika Onee-sama!” ]])\r\n\r\nLAYER_LOAD_FACE(\"BU_ERI01da\")\r\nPLAY_VOICE(\"erika_0256.wav\")\r\n    MSG([[\r\n    【Erika】sad\r\n “...Y-Yes.” ]])\r\nLAYER_LOAD_FACE(\"\")\r\n\r\n    MSG([[ I was dragged to the classroom by Hiyu without saying a word. ]])\r\n\r\n    LAYER_LOAD(50,\"\")\r\n    LAYER_LOAD(55,\"\")\r\n    LAYER_LOAD(60,\"\")\r\n    LAYER_LOAD(LAYER_BG,\"BG000aa\")\r\n    SWITCH_SCREEN(\"mask000\",1000,false)\r\n\r\n    --//BG：教室\r\n    LAYER_LOAD(LAYER_BG, \"BG014aa\")\r\n    SWITCH_SCREEN(\"mask015\" , 1000,false)\r\n\r\n    --//SE：ざわざわ\r\n--PLAY_SE(\"SEf003.wav\")\r\n\r\n    MSG([[ And here we are. ]])\r\n\r\n    PLAY_SE(\"SEf003.wav\",1000,true)\r\n    --//CG：着替えるクラスメイトに囲まれるエリカ。\r\n    LAYER_LOAD(LAYER_BG, \"EV010aa\")\r\n    SWITCH_SCREEN(\"mask000\" , 1000,false)\r\n\r\nPLAY_VOICE(\"schoolgirl_0063.wav\")\r\n    MSG([[\r\n    【Female student】\r\n “Tsudanuma-san, that bra is so cute. Where’d you buy it?” ]])\r\n    --//百合川咲夜\r\n\r\nPLAY_VOICE(\"schoolgirl_0064.wav\")\r\n    MSG([[\r\n    【Female student】\r\n “Ehehe, I found a great store in O-something. Yurikawa-san, you’re kinda flashy, huh?” ]])\r\n    --//津田沼芽々\r\n\r\nPLAY_VOICE(\"schoolgirl_0065.wav\")\r\n    MSG([[\r\n    【Female student】\r\n “Hehe, right? Well, I might not get a chance to meet guys, but I make sure to be prepared.” ]])\r\n    --//百合川咲夜\r\n\r\nPLAY_VOICE(\"erika_0257.wav\")\r\n    MSG([[\r\n    【Erika】\r\n (I can’t hear them... I can’t hear anything...) ]])\r\n\r\n    MSG([[ I lowered my gaze to the floor, trying not to listen to their conversation. ]])\r\n\r\n    MSG([[ I couldn’t eavesdrop on girls talking while changing. Not even a single word. ]])\r\n\r\n    MSG([[ I have to do my best not to hear any of it. ]])\r\n\r\n    MSG([[ It’s okay. If I remember my arrest technique training and keep calm, I can endure this trial―― ]])\r\n\r\nPLAY_VOICE(\"schoolgirl_0066.wav\")\r\n    MSG([[\r\n    【Female student】\r\n “Hey, wait! Nanajo-san’s chest is insane, isn’t it!? I thought it was volleyball!” ]])\r\n    --//百合川咲夜\r\n\r\nPLAY_VOICE(\"schoolgirl_0067.wav\")\r\n    MSG([[\r\n    【Female student】\r\n “This size is amazing... as expected from a politician's daughter.” ]])\r\n    --//平和堂依音\r\n\r\nPLAY_VOICE(\"schoolgirl_0068.wav\")\r\n    MSG([[\r\n    【Female student】\r\n “I-It’s not my papa’s fault!? That’s why I hate showing skin in front of people… ugh.” ]])\r\n    --//七条菜々那\r\n\r\n    MSG([[ Yeah, impossible to ignore!!! ]])\r\n\r\n    --//CG：着替えるクラスメイトに囲まれるエリカ（涙目）\r\n    LAYER_LOAD(LAYER_BG, \"EV010ad\")\r\n    SWITCH_SCREEN(\"mask000\" , 500,false)\r\n\r\n    --//effectフォント大\r\n    -- wiz : 要検討\r\n\r\n    MSG([[ There’s no way I can change in a situation like this. ]])\r\n\r\n    MSG([[ Especially since I’m still wearing my usual boxers underneath. If even a little of that is seen, I’d be stared at weirdly for sure. ]])\r\n\r\n    MSG([[ And on closer look―― ]])\r\n\r\n    STOP_SE(\"SEf003.wav\",1000)\r\n\r\n    --//CI：光る周囲の目 027\r\n    SWITCH_SCREEN(\"mask000\",0,false)\r\n    LAYER_LOAD(50,\"CI027a\")\r\n    LAYER_ALPHA(50,0)\r\n    --SWITCH_SCREEN(\"mask013\",1000,false)\r\n    LAYER_POSITION(50,1000,0)\r\n    LAYER_MOVE_ALPHA(50,255,500,Ease.Liner)\r\n    LAYER_MOVE_POSITION(50,0,0,500,Ease.OutSine)\r\n    --SWITCH_SCREEN(\"mask000\",500,false)\r\n    WAIT(500)\r\n\r\n    MSG([[ Everyone’s sneaking quick glances at me from the side! They’re probably curious about what kind of underwear the ‘Princess’ candidate wears. ]])\r\n\r\n    SWITCH_SCREEN(\"mask000\",0,false)\r\n    LAYER_MOVE_ALPHA(50,0,500,Ease.InSine)\r\n    LAYER_MOVE_POSITION(50,-1000,0,500,Ease.InSine)\r\n    WAIT(500)\r\n    LAYER_LOAD(50,\"\")\r\n    --SWITCH_SCREEN(\"mask014\",1000,false)\r\n\r\n    MSG([[ I definitely can’t change like this. What should I do… ]])\r\n\r\nPLAY_VOICE(\"hiyu_0131.wav\")\r\n    MSG([[\r\n    【Hiyu】\r\n “Erika Onee-sama? What’s wrong? Your face is bright red?” ]])\r\n\r\n    MSG([[ Hiyu asked me worriedly. ]])\r\n\r\n    MSG([[ Hiyu doesn’t seem interested in watching me change; she’s genuinely concerned. ]])\r\n\r\n    MSG([[ I’m sorry, but... I’ll have to rely on Hiyu’s help here. ]])\r\n\r\nPLAY_VOICE(\"erika_0258.wav\")\r\n    MSG([[\r\n    【Erika】\r\n “A-actually... I’m not used to exposing my skin in front of people. So I get really nervous...” ]])\r\n\r\nPLAY_VOICE(\"erika_0259.wav\")\r\n    MSG([[\r\n    【Erika】\r\n “If it’s okay... could you be my shield while I change, just for a little bit?” ]])\r\n\r\nPLAY_VOICE(\"hiyu_0132.wav\")\r\n    MSG([[\r\n    【Hiyu】\r\n “Hyubu!!!!!” ]])\r\n\r\nPLAY_VOICE(\"erika_0260.wav\")\r\n    MSG([[\r\n    【Erika】\r\n “Hiyu!?” ]])\r\n\r\n    MSG([[ Hiyu crouched down briefly with a nosebleed but then stood up. ]])\r\n\r\nPLAY_VOICE(\"hiyu_0133.wav\")\r\n    MSG([[\r\n    【Hiyu】\r\n “Haa... haa... I was holding back because I thought I’d pass out from staring at your changing, Onee-sama, but I never expected such a happy event.” ]])\r\n\r\nPLAY_VOICE(\"hiyu_0134.wav\")\r\n    MSG([[\r\n    【Hiyu】\r\n “Leave it to me, Erika Onee-sama. I won’t let a single ant set eyes on your changing!” ]])\r\n\r\n    MSG([[ She said that and stood in front of me, spreading her arms wide like a soccer goalkeeper. ]])\r\n\r\n    --//CG：着替えるクラスメイトに囲まれるエリカ（ヒユの盾）\r\n    LAYER_LOAD(LAYER_BG, \"EV010ab\")\r\n    SWITCH_SCREEN(\"mask000\" , 500,false)\r\n\r\nPLAY_VOICE(\"hiyu_0135.wav\")\r\n    MSG([[\r\n    【Hiyu】\r\n “Hyaaahhh!!! From this moment on, anyone who looks at Erika Onee-sama’s body will be dealt with by me!” ]])\r\n    --//CG：着替えるクラスメイトに囲まれるエリカ（ヒユの盾高速）\r\n    LAYER_LOAD(LAYER_BG, \"EV010ac\")\r\n    SWITCH_SCREEN(\"mask000\" , 500,false)\r\n\r\n    MSG([[ Then, somehow, Hiyu began moving side to side at super high speed repeatedly, completely blocking others’ views. ]])\r\n\r\n    MSG([[ A-amazing. It feels like she’s beyond any human limit. When she’s serious, Hiyu might actually be the strongest. ]])\r\n\r\nPLAY_VOICE(\"hiyu_0136.wav\")\r\n    MSG([[\r\n    【Hiyu】\r\n “Now, Onee-sama! Change while you can!” ]])\r\n\r\nPLAY_VOICE(\"erika_0261.wav\")\r\n    MSG([[\r\n    【Erika】\r\n “Y-Yeah. Thank you, Hiyu.” ]])\r\n\r\n    MSG([[ I hurriedly finished changing and somehow escaped the worst crisis... ]])\r\n\r\n    STOP_BGM(1000)\r\n\r\n    LAYER_LOAD(LAYER_BG,\"BG000aa\")\r\n    SWITCH_SCREEN(\"mask000\",1000,false)\r\n    WAIT_INPUT(1000)\r\n\r\n    MSG([[ Or so I thought. I had no idea that this slip-up would later cause a huge incident that would strangle me―― ]])\r\n\r\n    --//BG：グラウンド\r\n    LAYER_LOAD(LAYER_BG, \"BG012aa\")\r\n    SWITCH_SCREEN(\"mask000\" , 1000,false)\r\n\r\n    PLAY_BGM(\"BGM01.wav\")\r\n\r\n    MSG([[ The volleyball match between Class A and Class B in P.E. Neither side willing to give an inch, the game had reached its final stage―― ]])\r\n    --//BU、体操服リラ（真剣）、体操服ヒユ（焦り）\r\n    --LAYER_LOAD(50,\"BU_HIY03ga\")\r\n    LAYER_LOAD(55,\"BU_RIR04ba\")\r\n    LAYER_POSITION(55,700,0)\r\n    LAYER_MOVE_POSITION(55,400,0,500,Ease.OutCubic)\r\n    SWITCH_SCREEN(\"mask000\",500,false)\r\n\r\nPLAY_VOICE(\"lira_0086.wav\")\r\n    MSG([[\r\n    【Lira】gym uniform・serious\r\n “Kiriko, pass it to me! I’ll finish it with this spike!” ]])\r\n\r\nPLAY_VOICE(\"lira_0087.wav\")\r\n    MSG([[\r\n    【Lira】gym uniform・serious\r\n “Now, kneel, you weeds!” ]])\r\n\r\n    LAYER_LOAD(50,\"BU_HIY03ga\")\r\n    LAYER_POSITION(50,-700,0)\r\n    LAYER_MOVE_POSITION(50,-400,0,500,Ease.OutCubic)\r\n    SWITCH_SCREEN(\"mask000\",500,false)\r\n\r\nPLAY_VOICE(\"hiyu_0137.wav\")\r\n    MSG([[\r\n    【Hiyu】gym uniform・frantic\r\n “Hyaaaa! I have to make sure to pass it to Erika Onee-samaーーー!” ]])\r\n\r\n    --//SE：衝撃音\r\nPLAY_SE(\"SEc020.wav\")\r\n\r\n    LAYER_LOAD(50,\"\")\r\n    LAYER_LOAD(55,\"\")\r\n    LAYER_LOAD(LAYER_BG,\"BG000ab\")\r\n    SWITCH_SCREEN(\"mask000\",0,false)\r\n\r\n    --吉　空背景があればここで空に逃がす\r\n    --//SE：ボールのバウンド音（ポーン）\r\nPLAY_SE(\"SEb026.wav\")\r\n\r\n    LAYER_LOAD(50,\"BG012aa\")\r\n    LAYER_LOAD(55,\"BU_RIR04ga\")\r\n    LAYER_POSITION(55,650,0)\r\n    LAYER_MASK(56,\"frame00\",50,55)\r\n    SWITCH_SCREEN(\"mask000\",500,false)\r\n\r\nPLAY_VOICE(\"lira_0088.wav\")\r\n    MSG([[\r\n    【Lira】gym uniform・frantic\r\n “H-Hiyu’s hitting my attack with her face even while kneeling!?” ]])\r\n\r\nLAYER_LOAD_FACE(\"BU_ERI04ba\")\r\nPLAY_VOICE(\"erika_0262.wav\")\r\n    MSG([[\r\n    【Erika】gym uniform・serious\r\n “I believed in you, Hiyu!” ]])\r\nLAYER_LOAD_FACE(\"\")\r\n\r\n    LAYER_LOAD(60,\"BG012aa\")\r\n    LAYER_LOAD(65,\"BU_HIY03gb\")\r\n    LAYER_POSITION(65,-650,0)\r\n    LAYER_MASK(66,\"frame00r\",60,65)\r\n    SWITCH_SCREEN(\"mask000\",500,false)\r\n\r\nPLAY_VOICE(\"hiyu_0138.wav\")\r\n    MSG([[\r\n    【Hiyu】gym uniform・nosebleed frantic\r\n “Do it, Onee-samaーーーーーー!” ]])\r\n\r\nLAYER_LOAD_FACE(\"BU_ERI04bb\")\r\nPLAY_VOICE(\"erika_0263R.wav\")\r\n    MSG([[\r\n    【Erika】gym uniform・serious\r\n “We win, Lira!!!” ]])\r\nLAYER_LOAD_FACE(\"\")\r\n\r\n    LAYER_LOAD(50,\"\")\r\n    LAYER_LOAD(55,\"\")\r\n    LAYER_MASK(56,\"\")\r\n    LAYER_LOAD(60,\"\")\r\n    LAYER_LOAD(65,\"\")\r\n    LAYER_MASK(66,\"\")\r\n    LAYER_LOAD(LAYER_BG,\"BG012aa\")\r\n    LAYER_LOAD(55,\"BUL_RIR04ba\")\r\n    SWITCH_SCREEN(\"mask027\",500,false)\r\n\r\nPLAY_VOICE(\"lira_0089.wav\")\r\n    MSG([[\r\n    【Lira】gym uniform・serious\r\n “Fine then! Bring it on, Erika!!” ]])\r\n\r\n\r\n    --//SE：衝撃音\r\n    PLAY_SE(\"SEc020.wav\")\r\n    --WAIT(200)\r\n    LAYER_LOAD(50,\"\")\r\n    LAYER_LOAD(55,\"\")\r\n    LAYER_LOAD(LAYER_BG,\"BG000ab\")\r\n    SWITCH_SCREEN(\"mask027\",500,false)\r\n\r\n    --//SE：破裂音\r\nPLAY_SE(\"SEc041.wav\")\r\n--WAIT(500)\r\n\r\n    MSG([[ The moment Lira tried to receive my spike and touched the ball, it burst. ]])\r\n\r\n\r\n    --//SE：チャイム\r\n    PLAY_SE(\"SEb016.wav\")\r\n    --//BG：グラウンド\r\n    LAYER_LOAD(LAYER_BG, \"BG012aa\")\r\n    SWITCH_SCREEN(\"mask000\" , 1000,false)\r\n--WAIT(800)\r\n\r\n    MSG([[ At the same time, the bell rang. Looks like this match ended in a draw. ]])\r\n\r\n    --//BU、体操服リラ（悲しみ）、体操服ヒユ（鼻血真剣）\r\n    --LAYER_LOAD(50,\"BU_HIY03bb\")\r\n    LAYER_LOAD(55,\"BU_RIR04da\")\r\n    LAYER_POSITION(55,400,0)\r\n    SWITCH_SCREEN(\"mask000\",500,true)\r\n\r\nPLAY_VOICE(\"lira_0090.wav\")\r\n    MSG([[\r\n    【Lira】gym uniform・sad\r\n “Tch, we would’ve won if not for that. We need to order new balls from the office.” ]])\r\n\r\n    LAYER_LOAD(50,\"BU_HIY03bb\")\r\n    LAYER_POSITION(50,-400,0)\r\n    SWITCH_SCREEN(\"mask000\",500,true)\r\n\r\nPLAY_VOICE(\"hiyu_0139.wav\")\r\n    MSG([[\r\n    【Hiyu】gym uniform・serious・nosebleed\r\n “Y-You talk a lot. If the ball hadn’t burst, we’d have won with Erika Onee-sama’s powerful spike.” ]])\r\n\r\n    LAYER_LOAD(55,\"BU_RIR04ea\")\r\n    LAYER_POSITION(55,400,0)\r\n    SWITCH_SCREEN(\"mask000\",300,true)\r\n\r\nPLAY_VOICE(\"lira_0091.wav\")\r\n    MSG([[\r\n    【Lira】gym uniform・smile\r\n “Alright, alright. Nosebleeds, go to the infirmary already.” ]])\r\n\r\n    SWITCH_SCREEN(\"mask000\",0,false)\r\n    LAYER_MOVE_ALPHA(55,0,500,Ease.InSine)\r\n    LAYER_MOVE_POSITION(55,600,0,500,Ease.InSine)\r\n    WAIT(500)\r\n    LAYER_LOAD(55,\"\")\r\n\r\n    LAYER_LOAD(50,\"BU_HIY03db\")\r\n    LAYER_POSITION(50,-400,0)\r\n    SWITCH_SCREEN(\"mask000\",300,false)\r\n\r\nPLAY_VOICE(\"hiyu_0140.wav\")\r\n    MSG([[\r\n    【Hiyu】gym uniform・sad・nosebleed\r\n “Grr! Next time, I’ll definitely dedicate a victory to Erika Onee-sama!” ]])\r\n\r\nLAYER_LOAD_FACE(\"BU_ERI04fa\")\r\nPLAY_VOICE(\"erika_0264.wav\")\r\n    MSG([[\r\n    【Erika】gym uniform・wry smile\r\n “Hehe, as Lira says. Let's get you checked at the infirmary quickly.” ]])\r\n    LAYER_LOAD_FACE(\"\")\r\n\r\nSTOP_SE(\"SEb016.wav\")\r\n    SWITCH_SCREEN(\"mask000\",0,false)\r\n    LAYER_MOVE_ALPHA(50,0,500,Ease.InSine)\r\n    LAYER_MOVE_POSITION(50,-200,0,500,Ease.InSine)\r\n    WAIT(500)\r\n    LAYER_LOAD(50,\"\")\r\n\r\n    MSG([[ The P.E. class matches between the classes seem likely to continue for a while. ]])\r\n\r\n    MSG([[ Without the Princess Election in the mix, competing as a class is really fun. ]])\r\n\r\n    MSG([[ It’s tough figuring out how to change clothes, but now I’m a bit looking forward to future classes. ]])\r\n\r\n    MSG([[ Yet on the other hand, I feel a bit guilty for disguising my gender. ]])\r\n    --//BU：モブ体操服生徒Ａ・Ｂ・Ｅ\r\n    LAYER_LOAD(50,\"BU_MOB08ab\")\r\n    LAYER_LOAD(55,\"BU_MOB08ab\")\r\n    LAYER_LOAD(60,\"BU_MOB08ab\")\r\n    LAYER_POSITION(50,-800,0)\r\n    LAYER_POSITION(55,-200,0)\r\n    LAYER_POSITION(60,400,0)\r\n    LAYER_MOVE_POSITION(50,-600,0,500,Ease.OutSine)\r\n    LAYER_MOVE_POSITION(55,0,0,500,Ease.OutSine)\r\n    LAYER_MOVE_POSITION(60,600,0,500,Ease.OutSine)\r\n    SWITCH_SCREEN(\"mask000\",500,false)\r\n\r\nPLAY_VOICE(\"schoolgirl_0069.wav\")\r\n    MSG([[\r\n    【Female student】\r\n “Hey, did you watch the final direct match between Princess Lira and Princess Erika?” ]])\r\n\r\nPLAY_VOICE(\"lira-knight_0004.wav\")\r\n    MSG([[\r\n    【Female student】\r\n “Of course! It was seriously amazing! Both were completely even—true rivals.” ]])\r\n\r\nPLAY_VOICE(\"schoolgirl_0070.wav\")\r\n    MSG([[\r\n    【Female student】\r\n “I totally admire them as a fellow girl.” ]])\r\n\r\n    SWITCH_SCREEN(\"mask000\",0,false)\r\n    LAYER_MOVE_ALPHA(50,0,500,Ease.InSine)\r\n    LAYER_MOVE_ALPHA(55,0,500,Ease.InSine)\r\n    LAYER_MOVE_ALPHA(60,0,500,Ease.InSine)\r\n    LAYER_MOVE_POSITION(50,-400,0,500,Ease.InSine)\r\n    LAYER_MOVE_POSITION(55,200,0,500,Ease.InSine)\r\n    LAYER_MOVE_POSITION(60,800,0,500,Ease.InSine)\r\n    WAIT(500)\r\n    LAYER_LOAD(50,\"\")\r\n    LAYER_LOAD(55,\"\")\r\n    LAYER_LOAD(60,\"\")\r\n\r\nLAYER_LOAD_FACE(\"BU_ERI04da\")\r\nPLAY_VOICE(\"erika_0265.wav\")\r\n    MSG([[\r\n    【Erika】gym uniform・sad\r\n (...I’m actually a boy. Sorry.) ]])\r\nLAYER_LOAD_FACE(\"\")\r\n\r\n    MSG([[ Their words pinch my heart. ]])\r\n\r\n    MSG([[ Lira’s success comes from hard work. My success only comes from being ‘a boy.’ ]])\r\n\r\n    MSG([[ It’s not really a fair match despite the serious competition. I’m trampling on Lira, who desires a genuine challenge. ]])\r\n\r\nLAYER_LOAD_FACE(\"BU_ERI04aa\")\r\nPLAY_VOICE(\"erika_0266.wav\")\r\n    MSG([[\r\n    【Erika】gym uniform・normal\r\n “By the way, why is Lira so insistent on a serious competition?” ]])\r\nLAYER_LOAD_FACE(\"\")\r\n\r\n    --//BU、体操服ヒユ（通常・鼻血）\r\n    LAYER_LOAD(50,\"BU_HIY03ab\")\r\n    SWITCH_SCREEN(\"mask000\",500,true)\r\n\r\nPLAY_VOICE(\"hiyu_0141.wav\")\r\n    MSG([[\r\n    【Hiyu】gym uniform・normal・nosebleed\r\n “Erika Onee-sama? Is something wrong?” ]])\r\n\r\nLAYER_LOAD_FACE(\"BU_ERI04fa\")\r\nPLAY_VOICE(\"erika_0267.wav\")\r\n    MSG([[\r\n    【Erika】gym uniform・wry smile・sweat\r\n “Ah, sorry. I was just lost in thought.” ]])\r\nLAYER_LOAD_FACE(\"\")\r\n\r\n    MSG([[ Overthinking is a bad habit of mine. I shake off the unnecessary thoughts and smile at Hiyu. ]])\r\n\r\n    LAYER_LOAD(50,\"\")\r\n\r\n    --　　　　　◆\r\nSTOP_BGM(1000)\r\n    LAYER_LOAD(LAYER_BG, \"BG000aa\")\r\n    SWITCH_SCREEN(\"mask000\" , 1000,false)\r\n    WAIT_INPUT(1000)\r\n\r\n    ScenarioManager.Next(\"EP02_14\")\r\nend\r\n"
}