{
  "m_GameObject": {
    "m_FileID": 0,
    "m_PathID": 0
  },
  "m_Enabled": 1,
  "m_Script": {
    "m_FileID": 0,
    "m_PathID": -1707786903170945384
  },
  "m_Name": "EP03_20",
  "Path": "Assets/AddressableAssets/Lua/Scenario/EP03/EP03_20.lua",
  "Text": "function EP03_20()\r\n    --.転-2【8月第4週】「龍城院友梨の初恋」\r\n    SaveData.Title = \"龍城院友梨の初恋\"\r\n\r\n    --//BG：都会（昼）\r\n    LAYER_LOAD(LAYER_BG, \"BG008aa\")\r\n    SWITCH_SCREEN(\"mask000\" , 1000,false)\r\n\r\nPLAY_BGM(\"BGM06.wav\")\r\n\r\n    --//BU：モブ女子生徒Ｂ・Ｃ\r\n    LAYER_LOAD(50,\"BU_MOB05aa\")\r\n    LAYER_POSITION(50,400,0)\r\n    LAYER_LOAD(55,\"BU_MOB06aa\")\r\n    LAYER_POSITION(55,-400,0)\r\n    SWITCH_SCREEN(\"mask000\",500,true)\r\n\r\nPLAY_VOICE(\"yuhi_0001.wav\")\r\n    MSG([[\r\n    【Yuhi Takeda】\r\n \"Ryuguuin-chan, you really should start joining practice for the Hakuyosai soon, don't you think?\" ]])\r\n\r\nPLAY_VOICE(\"kaori_0001.wav\")\r\n    MSG([[\r\n    【Miu Kasasato】\r\n \"I understand the conservative standpoint... but I just can't bring myself to betray Sister Erika...\" ]])\r\n\r\nPLAY_VOICE(\"yuri_0030.wav\")\r\n    MSG([[\r\n    【Uran Ryuguuin】\r\n \"Then why don't just the two of you participate? I shall enjoy some window shopping alone.\" ]])\r\n\r\nPLAY_VOICE(\"yuhi_0002.wav\")\r\n    MSG([[\r\n    【Yuhi Takeda】\r\n \"W-wait!\" ]])\r\n\r\nPLAY_VOICE(\"kaori_0002.wav\")\r\n    MSG([[\r\n    【Miu Kasasato】\r\n \"It's dangerous to be alone, Ryuguuin-san!\" ]])\r\n\r\n    --//BU：なし\r\n    LAYER_LOAD(50,\"\")\r\n    LAYER_LOAD(55,\"\")\r\n    SWITCH_SCREEN(\"mask000\",500,true)\r\n\r\n    MSG([[ I slipped into the crowd and managed to shake off the two chasing me. ]])\r\n\r\n    MSG([[ —You say you don’t want to betray Sister Erika? I feel exactly the same way. ]])\r\n\r\n    MSG([[ At first, it was just a fleeting emotion. I was thrilled when I saw her protect Hiyu at the entrance ceremony and, blending with the classroom atmosphere, I casually called myself a \"knight.\" ]])\r\n\r\n    MSG([[ Being a “knight” at this academy isn’t anything special. ]])\r\n\r\n    MSG([[ But the more I learned, the more I was drawn to Sister Erika. ]])\r\n\r\n    --//effect：セピア加工（回想）\r\n    --FILTER_SCREEN(2)\r\n    --//CI：トランクスを穿いたエリカの写真が貼られた掲示 035\r\n    LAYER_LOAD(50,\"CI035a\")\r\n\tLAYER_EFFECT(50,2)\r\n    LAYER_POSITION(50,0,-200)\r\n    LAYER_MOVE_POSITION(50,0,0,500,Ease.OutSine)\r\n    SWITCH_SCREEN(\"mask000\",500,false)\r\n\r\n\r\n    MSG([[ The turning point was the infamous voyeurism incident. ]])\r\n\r\n    MSG([[ It was obvious that the faction led by Lira was behind it, yet Sister Erika didn’t seek retaliation at all and earnestly continued to improve herself. ]])\r\n\r\n    MSG([[ I realized she simply has no feelings to hate or harm anyone in the first place. ]])\r\n\r\n    LAYER_LOAD(50,\"\")\r\n    --//CG：ステージ上のエリカ（決意）\r\n    FILTER_SCREEN(2)\r\n    LAYER_LOAD(LAYER_BG, \"EVa001ab\")\r\n    SWITCH_SCREEN(\"mask000\" , 1000,false)\r\n    --//effect：セピア加工\r\n\r\n    MSG([[ Despite such kindness, she transforms completely on stage. When facing Lira on stage, Sister Erika was truly beautiful and magnificent, and my heart raced. ]])\r\n\r\n    MSG([[ Though I couldn’t relate to the talk of \"romance\" around me, ]])\r\n\r\n    MSG([[ it didn’t take long to realize this fluttering in my chest was \"first love.\" ]])\r\n\r\n    MSG([[ And at the same time, I noticed another feeling growing inside me._r That was jealousy toward the boys' division. ]])\r\n\r\nPLAY_VOICE(\"yuri_0031.wav\")\r\n    MSG([[\r\n    【Uran Ryuguuin】\r\n (I know it’s a love that will never come true, but still... it hurts to see Sister Erika spending time with a man.) ]])\r\n\r\nPLAY_VOICE(\"yuri_0032.wav\")\r\n    MSG([[\r\n    【Uran Ryuguuin】\r\n (I truly resent the man who steps into my irreplaceable garden.) ]])\r\n\r\nPLAY_VOICE(\"yuri_0033.wav\")\r\n    MSG([[\r\n    【Uran Ryuguuin】\r\n (And most of all, I hate... the shallow self that is driven by jealousy.) ]])\r\n\r\n    MSG([[ The other day, when I confided in Lady Uran and emotions flared, maybe it was because I wanted her to understand this feeling. ]])\r\n\r\n    MSG([[ A truly selfish woman. I scolded Sister Erika, but it’s really me who’s the most self-centered. ]])\r\n\r\n    MSG([[ In the end, all I want is for Sister Erika to pay more attention to me— ]])\r\n\r\nSTOP_BGM(1000)\r\n\r\n    LAYER_LOAD(LAYER_BG, \"BG008aa\")\r\n    FILTER_SCREEN(0)\r\n    --//BU：３号（素顔）\r\n    LAYER_LOAD(50,\"BU_SM301ab\")\r\n    SWITCH_SCREEN(\"mask000\" , 1000,false)\r\n\r\nPLAY_VOICE(\"senpai3_0041.wav\")\r\n    MSG([[\r\n    【????】\r\n \"So you're Ryuguin's daughter, huh?\" ]])\r\n\r\nPLAY_BGM(\"BGM05.wav\")\r\n\r\n    MSG([[ At that moment, I noticed an unfamiliar man standing before me. ]])\r\n\r\nPLAY_VOICE(\"yuri_0034.wav\")\r\n    MSG([[\r\n    【Uran Ryuguuin】\r\n \"Who are you? I don’t recognize you.\" ]])\r\n\r\nPLAY_VOICE(\"senpai3_0042.wav\")\r\n    MSG([[\r\n    【????】\r\n \"...Better if you don’t. Come along with me now.\" ]])\r\n\r\nPLAY_VOICE(\"yuri_0035.wav\")\r\n    MSG([[\r\n    【Uran Ryuguuin】\r\n \"Nnnh!?\" ]])\r\n\r\n    LAYER_LOAD(50,\"\")\r\n    LAYER_LOAD(LAYER_BG,\"BG000aa\")\r\n    SWITCH_SCREEN(\"mask029\",500,false)\r\n\r\n    MSG([[ My mouth was quickly bound with a cloth and I couldn’t make a sound. Despite the crowd around, how bold. ]])\r\n\r\n    MSG([[ But his movements were so swift that no one nearby noticed or stopped him. ]])\r\n\r\n    MSG([[ I was dragged along into an alleyway without resistance— ]])\r\n\r\nPLAY_VOICE(\"yuri_0036.wav\")\r\n    MSG([[\r\n    【Uran Ryuguuin】\r\n (H-help...) ]])\r\n\r\nPLAY_VOICE(\"yuri_0037.wav\")\r\n    MSG([[\r\n    【Uran Ryuguuin】\r\n (Help me, Sister Erika!) ]])\r\n\r\n    MSG([[ I called the name of my beloved in my heart. ]])\r\n\r\n    --//BU：エリカ（夏服・真剣）\r\n    LAYER_LOAD(LAYER_BG,\"BG008aa\")\r\n    LAYER_LOAD(55,\"BUL_ERI02bb\")\r\n    SWITCH_SCREEN(\"mask027\",300,false)\r\n\r\nPLAY_VOICE(\"erika_0619.wav\")\r\n    MSG([[\r\n    【Erika】\r\n \"—Ryuguuin-san!\" ]])\r\n\r\n    MSG([[ From the crowd emerged a beautiful silver figure. In an instant, a fierce kick struck the man’s abdomen and the strength of the arm restraining me relaxed. ]])\r\n\r\n    MSG([[ Seizing the opportunity, I forgot all shyness and embraced Sister Erika. ]])\r\n\r\nPLAY_VOICE(\"yuri_0038.wav\")\r\n    MSG([[\r\n    【Uran Ryuguuin】\r\n \"Sister... Sister...\" ]])\r\n\r\n    LAYER_LOAD(55,\"BUL_ERI02ea\")\r\n    SWITCH_SCREEN(\"mask000\",300,true)\r\n\r\nPLAY_VOICE(\"erika_0620.wav\")\r\n    MSG([[\r\n    【Erika】\r\n \"It’s okay now. You must have been scared. I’m glad I got here in time.\" ]])\r\n\r\n    --//BU：３号（素顔）、エリカ（夏服・真剣）\r\n    LAYER_LOAD(50,\"BU_SM301ab\")\r\n    LAYER_POSITION(50,600,0)\r\n    SWITCH_SCREEN(\"mask000\",500,true)\r\n\r\nPLAY_VOICE(\"senpai3_0043.wav\")\r\n    MSG([[\r\n    【????】\r\n \"What, you’ve got a bodyguard? That’s not what I was told.\" ]])\r\n\r\nPLAY_VOICE(\"senpai3_0044.wav\")\r\n    MSG([[\r\n    【????】\r\n \"...Well then, I guess we’ll be leaving for now.\" ]])\r\n\r\n    LAYER_LOAD(55,\"BUL_ERI02ba\")\r\n    SWITCH_SCREEN(\"mask000\",300,true)\r\n\r\nPLAY_VOICE(\"erika_0621.wav\")\r\n    MSG([[\r\n    【Erika】\r\n \"Do you think I’ll let you escape? I’m very angry right now. Let’s bring the police into this.\" ]])\r\n\r\nPLAY_VOICE(\"senpai3_0045.wav\")\r\n    MSG([[\r\n    【????】\r\n \"Then try to follow me. While you chase me, this lady might be in danger... heh heh.\" ]])\r\n\r\n    SWITCH_SCREEN(\"mask000\",0,false)\r\n    LAYER_MOVE_ALPHA(50,0,500,Ease.InCubic)\r\n    LAYER_MOVE_POSITION(50,800,0,500,Ease.InCubic)\r\n    WAIT(500)\r\n    LAYER_LOAD(50,\"\")\r\n\r\n    --//BU：エリカ（夏服・焦り）\r\n    LAYER_LOAD(55,\"BUL_ERI02ga\")\r\n    SWITCH_SCREEN(\"mask000\",300,false)\r\n\r\nPLAY_VOICE(\"erika_0622.wav\")\r\n    MSG([[\r\n    【Erika】\r\n \"Ugh...!\" ]])\r\n\r\nSTOP_BGM(1000)\r\n\r\n    MSG([[ Sister Erika watched bitterly as the man ran away. ]])\r\n\r\n    MSG([[ Her hand gripped mine tightly so as not to let go. ]])\r\n\r\n    MSG([[ Even though she must desperately want to chase after him. Yet even in a time like this, she puts others first. ]])\r\n\r\n    MSG([[ She is endlessly kindhearted. I feel foolish for having doubted her as an 'intruder' even for a moment. ]])\r\n\r\nPLAY_VOICE(\"yuri_0039.wav\")\r\n    MSG([[\r\n    【Uran Ryuguuin】\r\n \"Th-thank you, Sister Erika. But why are you in this town?\" ]])\r\n\r\n    LAYER_LOAD(55,\"BUL_ERI02aa\")\r\n    SWITCH_SCREEN(\"mask000\",300,true)\r\n\r\nPLAY_BGM(\"BGM06.wav\")\r\n\r\nPLAY_VOICE(\"erika_0623.wav\")\r\n    MSG([[\r\n    【Erika】\r\n \"Lira gathered information from friends and compiled a list of places where those resting often go out.\" ]])\r\n\r\n    LAYER_LOAD(55,\"BUL_ERI02ea\")\r\n    SWITCH_SCREEN(\"mask000\",300,true)\r\n\r\nPLAY_VOICE(\"erika_0624.wav\")\r\n    MSG([[\r\n    【Erika】\r\n \"The gal information network is incredible. She quickly found the place the three of you—Ryuguuin-san and the others—have been visiting a lot recently, so she found Takeda-san and Miu-san as well.\" ]])\r\n\r\nPLAY_VOICE(\"erika_0625.wav\")\r\n    MSG([[\r\n    【Erika】\r\n \"Since I heard you were acting alone, I was worried and searched for you.\" ]])\r\n\r\n    LAYER_LOAD(55,\"BUL_ERI02fa\")\r\n    SWITCH_SCREEN(\"mask000\",300,true)\r\n\r\nPLAY_VOICE(\"erika_0626.wav\")\r\n    MSG([[\r\n    【Erika】\r\n \"Though I didn’t expect to run into such a dangerous situation...\" ]])\r\n\r\n    MSG([[ —Why did you save me?_r I was about to ask but stopped myself. ]])\r\n\r\n    MSG([[ I could easily imagine the nonsensical answer I’d get. ]])\r\n\r\n    MSG([[ After all, there’s no option inside Sister Erika’s heart for \"not helping.\" ]])\r\n\r\nPLAY_VOICE(\"yuri_0040.wav\")\r\n    MSG([[\r\n    【Uran Ryuguuin】\r\n \"So why were you looking for me? You’re not here begging me to join the play practice, are you?\" ]])\r\n\r\n    MSG([[ I’m grateful for the rescue, but that’s a separate matter. ]])\r\n\r\n    MSG([[ No matter how much it’s Sister Erika asking, I won’t easily accept a joint practice with the boys’ division. If it’s a blind request, I’ll naturally reject it. ]])\r\n\r\n    MSG([[ However, an unexpected reply came from Sister Erika. ]])\r\n\r\n    LAYER_LOAD(55,\"BUL_ERI02aa\")\r\n    SWITCH_SCREEN(\"mask000\",300,true)\r\n\r\nPLAY_VOICE(\"erika_0627.wav\")\r\n    MSG([[\r\n    【Erika】\r\n \"I won’t be asking. I’m here to make a proposal today.\" ]])\r\n\r\n    LAYER_LOAD(55,\"BUL_ERI02ea\")\r\n    SWITCH_SCREEN(\"mask000\",300,true)\r\n\r\nPLAY_VOICE(\"erika_0628.wav\")\r\n    MSG([[\r\n    【Erika】\r\n \"A wonderful improvement plan even those uncomfortable with boys will want to join.\" ]])\r\n\r\nPLAY_VOICE(\"yuri_0041.wav\")\r\n    MSG([[\r\n    【Uran Ryuguuin】\r\n \"Wh-what is that? There’s no way such a convenient idea exists.\" ]])\r\n\r\nPLAY_VOICE(\"erika_0629.wav\")\r\n    MSG([[\r\n    【Erika】\r\n \"Please at least hear me out. Actually, well—\" ]])\r\n\r\n    LAYER_LOAD(55,\"\")\r\n    LAYER_LOAD(LAYER_BG,\"BG000aa\")\r\n    SWITCH_SCREEN(\"mask015\",1000,false)\r\n\r\n    LAYER_LOAD(LAYER_BG,\"BG008aa\")\r\n    LAYER_LOAD(55,\"BUL_ERI02aa\")\r\n    SWITCH_SCREEN(\"mask015\",1000,false)\r\n\r\nPLAY_VOICE(\"yuri_0042.wav\")\r\n    MSG([[\r\n    【Uran Ryuguuin】\r\n \"Eh—!? Th-that’s absurd—\" ]])\r\n\r\n    MSG([[ The play concept I heard from Sister Erika was far too outrageous. ]])\r\n\r\n    MSG([[ It’s just like during the Princess Election with Lira. Once again, she is trying to break the conventions of Yuriai Private Academy with bold ideas and courage. ]])\r\n\r\n    MSG([[ As a conservative, it’s a proposal I can never accept. But— ]])\r\n\r\nPLAY_VOICE(\"yuri_0043.wav\")\r\n    MSG([[\r\n    【Uran Ryuguuin】\r\n (Sister Erika... your shoes are all worn out.) ]])\r\n\r\nPLAY_VOICE(\"yuri_0044.wav\")\r\n    MSG([[\r\n    【Uran Ryuguuin】\r\n (You said you found us immediately, but this town is huge. You must have been scrambling around a lot.) ]])\r\n\r\nPLAY_VOICE(\"yuri_0045.wav\")\r\n    MSG([[\r\n    【Uran Ryuguuin】\r\n (And surely... you’re determined to keep running until every absentee participates.) ]])\r\n\r\n    MSG([[ What an awkward person. At this rate, she might collapse someday. ]])\r\n\r\n    MSG([[ No, knowing her, she’ll keep running until she can’t move anymore, no matter how many times she falls. ]])\r\n\r\n    MSG([[ That’s just who she is. So everyone naturally falls in love with her. ]])\r\n\r\n    MSG([[ Just like I did. ]])\r\n\r\nPLAY_VOICE(\"yuri_0046.wav\")\r\n    MSG([[\r\n    【Uran Ryuguuin】\r\n \"I understand. I’ll take Sister Erika’s passion to heart and start attending practice from tomorrow.\" ]])\r\n\r\nPLAY_VOICE(\"yuri_0047.wav\")\r\n    MSG([[\r\n    【Uran Ryuguuin】\r\n \"So please, Sister Erika, get some rest too. You look worn out.\" ]])\r\n\r\n    LAYER_LOAD(55,\"BUL_ERI02ea\")\r\n    SWITCH_SCREEN(\"mask000\",300,true)\r\n\r\nPLAY_VOICE(\"erika_0630.wav\")\r\n    MSG([[\r\n    【Erika】\r\n \"Thank you so much, Ryuguuin-san!\" ]])\r\n\r\nPLAY_VOICE(\"erika_0631.wav\")\r\n    MSG([[\r\n    【Erika】\r\n \"Of course I won’t push myself! I’ll just keep reaching out in ways I can do!\" ]])\r\n\r\n    MSG([[ All lies. This person will just keep trying too hard anyway. ]])\r\n\r\n    MSG([[ Then all I can do is stay beside this awkward her and keep supporting her. ]])\r\n\r\nPLAY_VOICE(\"yuri_0048.wav\")\r\n    MSG([[\r\n    【Uran Ryuguuin】\r\n (I have fallen for such a troublesome person.) ]])\r\n\r\n\r\nLAYER_LOAD(55,\"\")\r\nLAYER_LOAD(LAYER_BG,\"BG000aa\")\r\nSWITCH_SCREEN(\"mask000\",1000,false)\r\nWAIT_INPUT(1000)\r\n\r\nLAYER_LOAD(LAYER_BG,\"BG002aa\")\r\nSWITCH_SCREEN(\"mask000\",1000,false)\r\n\r\n\r\n    MSG([[ Afterwards, Sister Erika led me to join Lira, and we met up with Takeda-san and Miu-san. They saw me off to the station. ]])\r\n\r\n    LAYER_LOAD(55,\"BUL_ERI02aa\")\r\n    SWITCH_SCREEN(\"mask000\",500,true)\r\n\r\nPLAY_VOICE(\"erika_0632.wav\")\r\n    MSG([[\r\n    【Erika】\r\n \"I have to meet someone else with Lira, so I’ll leave you here.\" ]])\r\n\r\n    LAYER_LOAD(55,\"BUL_ERI02ea\")\r\n    SWITCH_SCREEN(\"mask000\",300,true)\r\n\r\nPLAY_VOICE(\"erika_0633.wav\")\r\n    MSG([[\r\n    【Erika】\r\n \"See you again at the academy.\" ]])\r\n\r\nPLAY_VOICE(\"yuri_0049.wav\")\r\n    MSG([[\r\n    【Uran Ryuguuin】\r\n \"Yes, see you at the academy. I love you, Sister Erika.\" ]])\r\n\r\n    LAYER_LOAD(55,\"BUL_ERI02fc\")\r\n    SWITCH_SCREEN(\"mask000\",300,true)\r\n\r\nPLAY_VOICE(\"erika_0634.wav\")\r\n    MSG([[\r\n    【Erika】\r\n \"Thank you. I love you too, Ryuguuin-san.\" ]])\r\n\r\n    SWITCH_SCREEN(\"mask000\",0,false)\r\n    LAYER_MOVE_ALPHA(55,0,500,Ease.InSine)\r\n    LAYER_MOVE_POSITION(55,200,0,500,Ease.InSine)\r\n    WAIT(500)\r\n    LAYER_LOAD(55,\"\")\r\n\r\nPLAY_VOICE(\"yuri_0050.wav\")\r\n    MSG([[\r\n    【Uran Ryuguuin】\r\n \"...Liar.\" ]])\r\n\r\n    MSG([[ I parted with Sister Erika and looked up at the sky alone. ]])\r\n\r\n    --//BG：好天の青空\r\n    LAYER_LOAD(LAYER_BG,\"Sprite/BG027aa.png\")\r\n    LAYER_POSITION(LAYER_BG,1080,1250)\r\n    -- LAYER_MOVE_POSITION(LAYER_BG,1080,1150,3000,Ease.OutSine)\r\n    SWITCH_SCREEN(\"mask000\",1000,false)\r\n\r\n    MSG([[ A cloudless, fine day. As if mirroring my current feelings, it was completely clear. ]])\r\n\r\n    MSG([[ I’ve made up my mind. ]])\r\n\r\n    MSG([[ Even if this love never comes true. Even if my body is burned by the flames of jealousy. ]])\r\n\r\n    MSG([[ I will keep my feelings locked away and continue to adore Sister Erika. ]])\r\n\r\nSTOP_BGM(2000)\r\n    --　　　　　◆\r\n    LAYER_LOAD(LAYER_BG, \"BG000aa\")\r\n    SWITCH_SCREEN(\"mask000\" , 1000,false)\r\n    WAIT_INPUT(1000)\r\n\r\n    --//BG：都会（昼）\r\n    LAYER_LOAD(LAYER_BG, \"BG008aa\")\r\n\r\n    --//BU：リラ（夏服・通常）\r\n    LAYER_LOAD(50,\"BU_RIR02aa\")\r\n    SWITCH_SCREEN(\"mask003\" , 1000,false)\r\n\r\n    MSG([[ The persuasion of Ryuguuin and the others has somehow been settled safely. Apparently, a game enthusiast named Setsuko Sero frequents a game center in this town, so next I have to head there. ]])\r\n\r\nPLAY_BGM(\"BGM02.wav\")\r\n\r\n    LAYER_LOAD(50,\"BU_RIR02ba\")\r\n    SWITCH_SCREEN(\"mask000\",300,true)\r\n\r\nPLAY_VOICE(\"lira_0313.wav\")\r\n    MSG([[\r\n    【Lira】\r\n \"Hey Erika. Take a little break.\" ]])\r\n\r\nPLAY_VOICE(\"lira_0314.wav\")\r\n    MSG([[\r\n    【Lira】\r\n \"I get you want to see everyone ASAP, but you clearly look exhausted.\" ]])\r\n\r\n    LAYER_LOAD(50,\"BU_RIR02aa\")\r\n    SWITCH_SCREEN(\"mask000\",300,true)\r\n\r\nPLAY_VOICE(\"lira_0315.wav\")\r\n    MSG([[\r\n    【Lira】\r\n \"You were working late last night too, you know. No pushing yourself, okay?\" ]])\r\n\r\nLAYER_LOAD_FACE(\"BU_ERI02da\")\r\nPLAY_VOICE(\"erika_0635.wav\")\r\n    MSG([[\r\n    【Erika】\r\n \"I-I'm sorry... I just wanted to share the improvement plans everyone worked on as soon as possible.\" ]])\r\nLAYER_LOAD_FACE(\"\")\r\n\r\n    LAYER_LOAD(50,\"BU_RIR02ea\")\r\n    SWITCH_SCREEN(\"mask000\",300,true)\r\n\r\nPLAY_VOICE(\"lira_0316.wav\")\r\n    MSG([[\r\n    【Lira】\r\n \"Well, that earnestness is one of your charms~\" ]])\r\n\r\n    LAYER_LOAD(50,\"BU_RIR02ia\")\r\n    SWITCH_SCREEN(\"mask000\",300,true)\r\n\r\nPLAY_VOICE(\"lira_0317.wav\")\r\n    MSG([[\r\n    【Lira】\r\n \"First, let’s fuel up at the nearby ramen shop.\" ]])\r\n\r\nLAYER_LOAD_FACE(\"BU_ERI02fc\")\r\nPLAY_VOICE(\"erika_0636.wav\")\r\n    MSG([[\r\n    【Erika】\r\n \"Thank you. An empty stomach won’t do for Erika Ikusa.<sprite=\"Emoji\" name=\"note\">\" ]])\r\nLAYER_LOAD_FACE(\"\")\r\n\r\n    LAYER_LOAD(50,\"BU_RIR02da\")\r\n    SWITCH_SCREEN(\"mask000\",300,true)\r\n\r\nPLAY_VOICE(\"lira_0318.wav\")\r\n    MSG([[\r\n    【Lira】\r\n \"...Are you joking? Hey, was that a joke just now?\" ]])\r\n\r\nLAYER_LOAD_FACE(\"BU_ERI02ea\")\r\nPLAY_VOICE(\"erika_0637.wav\")\r\n    MSG([[\r\n    【Erika】\r\n \"...?\" ]])\r\nLAYER_LOAD_FACE(\"\")\r\n\r\nPLAY_VOICE(\"lira_0319.wav\")\r\n    MSG([[\r\n    【Lira】\r\n \"Sigh~~~~ Both Uran-senpai and you... oblivious types are the scariest.\" ]])\r\n\r\n    SWITCH_SCREEN(\"mask000\",0,false)\r\n    LAYER_MOVE_ALPHA(50,0,500,Ease.InSine)\r\n    LAYER_MOVE_POSITION(50,200,0,500,Ease.InSine)\r\n    WAIT(500)\r\n    LAYER_LOAD(50,\"\")\r\n\r\n    MSG([[ For some reason, Lira looked exasperated as she pulled me firmly by the hand and led me to the ramen shop. ]])\r\n\r\n    MSG([[ But really, who was that man targeting Ryuguuin earlier? ]])\r\n\r\n    MSG([[ His movements, and how quickly he recovered after my kick— he didn’t seem like an amateur at all. ]])\r\n\r\nLAYER_LOAD_FACE(\"BU_ERI02ba\")\r\nPLAY_VOICE(\"erika_0638.wav\")\r\n    MSG([[\r\n    【Erika】\r\n (…He’s someone unrelated to the academy, isn’t he?) ]])\r\nLAYER_LOAD_FACE(\"\")\r\n\r\n    MSG([[ He seemed extremely cautious of me, and the Ryuguuin family has been alerted, so it should be okay for a while. ]])\r\n\r\n    MSG([[ But the unease in my chest wouldn’t easily disappear. ]])\r\n    --　　　　◆\r\nSTOP_BGM(1000)\r\n    LAYER_LOAD(50,\"\")\r\n    LAYER_LOAD(LAYER_BG, \"BG000aa\")\r\n    SWITCH_SCREEN(\"mask000\" , 1000,false)\r\n    WAIT_INPUT(1000)\r\n\r\n    ScenarioManager.Next(\"EP03_21\")\r\nend\r\n"
}