{
  "m_GameObject": {
    "m_FileID": 0,
    "m_PathID": 0
  },
  "m_Enabled": 1,
  "m_Script": {
    "m_FileID": 0,
    "m_PathID": -1707786903170945384
  },
  "m_Name": "EP04_04",
  "Path": "Assets/AddressableAssets/Lua/Scenario/EP04/RIR/EP04_04.lua",
  "Text": "function RIR_EP04_04()\r\n    -- .起-2【11月第2週】「仮装恋愛」\r\n    SaveData.Title = \"仮装恋愛\"\r\n\r\n    -- //BG：1-A教室（夕方）\r\n    LAYER_LOAD(LAYER_BG, \"BG014ba\")\r\n    SWITCH_SCREEN(\"mask000\" , 1000,false)\r\n\r\n    MSG([[That afternoon after school, while waiting in the classroom, Lira-san arrived as promised.\r\nその日の放課後、教室で待っていると、約束通りリラさんがやってきた。]])\r\n\r\nPLAY_BGM(\"BGM08.wav\")\r\n\r\n    -- //BU：リラ（苦笑）\r\n    LAYER_LOAD(50,\"BU_RIR07fc\")\r\n    LAYER_POSITION(50,200,0)\r\n    LAYER_MOVE_POSITION(50,0,0,500,Ease.OutSine)\r\n    SWITCH_SCREEN(\"mask000\",500,false)\r\n\r\nPLAY_VOICE(\"lira_0659.wav\")\r\n    MSG([[\r\n【Lira】\r\n苦笑 \"Sorry to keep you waiting. It's bad of me to have made you cancel an important meeting for my sake.\"\r\n苦笑\r\n    「ごめん、お待たせ。悪いね、アタシのために大事な話し合いをキャンセルさせちゃって」]])\r\n\r\nLAYER_LOAD_FACE(\"BU_ERI01ea\")\r\nPLAY_VOICE(\"erika_1378.wav\")\r\n    MSG([[\r\n【Erika】\r\n笑顔 \"That's alright. Lira-san, you seemed different since this morning, so I was worried.\"\r\n笑顔\r\n    「いいんですよ。リラさん、今朝からいつもと様子が違っていたから心配していたんです」]])\r\n\r\nLAYER_LOAD_FACE(\"BU_ERI01aa\")\r\nPLAY_VOICE(\"erika_1379.wav\")\r\n    MSG([[\r\n【Erika】\r\n通常 \"So, what exactly did you want to talk about?\"\r\n通常\r\n    「それで、一体どのような用件だったんですか？」]])\r\nLAYER_LOAD_FACE(\"\")\r\n\r\n    LAYER_LOAD(50,\"BU_RIR07fa\")\r\n    SWITCH_SCREEN(\"mask000\",300,true)\r\n\r\nPLAY_VOICE(\"lira_0660.wav\")\r\n    MSG([[\r\n【Lira】\r\n苦笑・汗 \"Ah, um, well, that is...\"\r\n苦笑・汗\r\n    「あー、えーっと、それはねー……」]])\r\n\r\n    MSG([[Lira-san, unusually hesitant, fidgeted with her hands awkwardly.\r\nリラさんが珍しく、言いにくそうに手をモジモジさせる。]])\r\n\r\n    LAYER_LOAD(50,\"BU_RIR07hb\")\r\n    SWITCH_SCREEN(\"mask000\",300,true)\r\n\r\nPLAY_VOICE(\"lira_0661.wav\")\r\n    MSG([[\r\n【Lira】\r\n赤面 \"Actually, well... my twin sister Riko apparently likes someone.\"\r\n赤面\r\n    「実は、その……アタシの双子の妹のリコがさ、好き、らしいんだわ」]])\r\n\r\nLAYER_LOAD_FACE(\"BU_ERI01ca\")\r\nPLAY_VOICE(\"erika_1380.wav\")\r\n    MSG([[\r\n【Erika】\r\n驚き \"Likes? Riko-san? Likes who?\"\r\n驚き\r\n    「好き？　リコさんが？　何をですか？」]])\r\nLAYER_LOAD_FACE(\"\")\r\n\r\nPLAY_VOICE(\"lira_0662.wav\")\r\n    MSG([[\r\n【Lira】\r\n赤面 \"Uh... you know... your cousin.\"\r\n赤面\r\n    「えぇっと……ほ、ほら……アンタの、従兄」]])\r\n\r\nLAYER_LOAD_FACE(\"BU_ERI01ca\")\r\nPLAY_VOICE(\"erika_1381.wav\")\r\n    MSG([[\r\n【Erika】\r\n驚き \"Cousin?\"\r\n驚き\r\n    「従妹？」]])\r\nLAYER_LOAD_FACE(\"\")\r\n\r\n    MSG([[Huh? What does that mean?\r\nえ？\r\n    　どういう、ことでしょう？]])\r\n\r\nLAYER_LOAD_FACE(\"BU_ERI01ca\")\r\nPLAY_VOICE(\"erika_1382.wav\")\r\n    MSG([[\r\n【Erika】\r\n驚き \"Did I ever introduce my cousin?\"\r\n驚き\r\n    「私の従妹、紹介してましたっけ？」]])\r\nLAYER_LOAD_FACE(\"\")\r\n\r\n    LAYER_LOAD(50,\"BU_RIR07ga\")\r\n    SWITCH_SCREEN(\"mask000\",300,true)\r\n\r\nPLAY_VOICE(\"lira_0663.wav\")\r\n    MSG([[\r\n【Lira】\r\n焦り \"Y-Yes, yes! You definitely introduced her to us!\"\r\n焦り\r\n    「し、してたしてた！　ちゃんと紹介してもらってたって！」]])\r\n\r\nPLAY_VOICE(\"lira_0664.wav\")\r\n    MSG([[\r\n【Lira】\r\n焦り \"So I mean—not me—I mean Riko was able to get in touch! You even exchanged RINE contacts, right!?\"\r\n焦り\r\n    「だからアタシ――じゃなかった！　リコは連絡をとれてたワケで！　ＲＩＮＥも交換してたでしょ！？」]])\r\n\r\nLAYER_LOAD_FACE(\"BU_ERI01ga\")\r\nPLAY_VOICE(\"erika_1383.wav\")\r\n    MSG([[\r\n【Erika】\r\n焦り \"W-What? Ah—\"\r\n焦り\r\n    「え？　え？　あ――」]])\r\nLAYER_LOAD_FACE(\"\")\r\n\r\n    MSG([[Cousin... no way...\r\nいとこ、って……ま、まさか……。]])\r\n\r\n    LAYER_LOAD(50,\"BU_RIR07ba\")\r\n    SWITCH_SCREEN(\"mask000\",300,true)\r\n\r\nPLAY_VOICE(\"lira_0665.wav\")\r\n    MSG([[\r\n【Lira】\r\n真剣 \"Riko has liked Minato-kun for a while now! Seriously! I mean seriously, seriously!\"\r\n真剣\r\n    「リコは前々から、ミナトくんのことを好きだったの！　マジで！　本気と書いてマジ！ 」]])\r\n\r\nLAYER_LOAD_FACE(\"BU_ERI01ha\")\r\nPLAY_VOICE(\"erika_1384.wav\")\r\n    MSG([[\r\n【Erika】\r\n赤面 \"Fwaa...\"\r\n赤面\r\n    「ふぇぇ……」]])\r\nLAYER_LOAD_FACE(\"\")\r\n\r\n    MSG([[For the first time in my life, I was confessed to. Well, right now I'm Erika, so it's secondhand, but still.\r\n生まれて初めて、告白されちゃった。\r\n    　いや、今のボクはエリカだし、又聞きなんだけど。]])\r\n\r\n    MSG([[Ugh, I don't know how I should react...\r\nうう、どういう反応すればいいか、わからない……。]])\r\n\r\n    LAYER_LOAD(50,\"BU_RIR07ha\")\r\n    SWITCH_SCREEN(\"mask000\",300,true)\r\n\r\nPLAY_VOICE(\"lira_0666.wav\")\r\n    MSG([[\r\n【Lira】\r\n赤面 \"It's not like you should be embarrassed... I was surprised when Riko told me too, and even now my heart feels like it's gonna burst.\"\r\n赤面 「いや、別にアンタが恥ずかしがることじゃないでしょ……アタシもリコから話を聞いた時はビックリしたし、今だって心臓が飛び出そうだけどさ」]])\r\n\r\nLAYER_LOAD_FACE(\"BU_ERI01ha\")\r\nPLAY_VOICE(\"erika_1385.wav\")\r\n    MSG([[\r\n【Erika】\r\n赤面 \"Y-Yes, that's right! Sorry... It's just that being so close to Minato, it's hard to think of it like someone else's matter...\"\r\n赤面\r\n    「そそそ、そうですよね！　ごめんなさい…！　何だか、ミナトとは距離が近すぎて、他人事に思えなくって……」]])\r\nLAYER_LOAD_FACE(\"\")\r\n\r\n    MSG([[Actually, it’s not someone else’s matter...\r\n実際他人事じゃありませんし……。]])\r\n\r\n    MSG([[I desperately forced my heart, which felt like it might jump out, to calm down.\r\nボクはもう必死になって、今にも飛び出そうな心臓を無理やりに落ち着かせた。]])\r\n\r\n    LAYER_LOAD(50,\"BU_RIR07aa\")\r\n    SWITCH_SCREEN(\"mask000\",300,true)\r\n\r\nPLAY_VOICE(\"lira_0667.wav\")\r\n    MSG([[\r\n【Lira】\r\n通常 \"Getting to the point, Erika, I want you to help bring Riko and Minato-kun together.\"\r\n通常\r\n    「本題に入るとさ、エリカにはリコとミナトくんをくっつける手伝いをして欲しいんだよ」]])\r\n\r\n    LAYER_LOAD(50,\"BU_RIR07ga\")\r\n    SWITCH_SCREEN(\"mask000\",300,true)\r\n\r\nPLAY_VOICE(\"lira_0668.wav\")\r\n    MSG([[\r\n【Lira】\r\n焦り \"Ah! Of course, if Minato-kun already has a girlfriend... then the story’s totally different.\"\r\n焦り\r\n    「あ！　も、もちろんアレだよ？　もうミナトくんに彼女がいたら……話は全然変わってくるんだけどさ」]])\r\n\r\nLAYER_LOAD_FACE(\"BU_ERI01ga\")\r\nPLAY_VOICE(\"erika_1386.wav\")\r\n    MSG([[\r\n【Erika】\r\n焦り \"N-No! That’s not the case at all! There's no girlfriend whatsoever!\"\r\n焦り\r\n    「い、いや！　そんなことは全然！　彼女のカの字もないんですけど！」]])\r\n\r\nLAYER_LOAD_FACE(\"BU_ERI01fa\")\r\nPLAY_VOICE(\"erika_1387.wav\")\r\n    MSG([[\r\n【Erika】\r\n苦笑・汗 \"Being so close, I don’t really get why Minato’s so appealing. Um… why do you think Riko fell for Minato?\"\r\n苦笑・汗\r\n    「近くにいると、全然ミナトの魅力ってわからないんですよね。あの……どうしてリコさんは、ミナトを好きになったんでしょう」]])\r\n\r\nPLAY_VOICE(\"erika_1388.wav\")\r\n    MSG([[\r\n【Erika】\r\n苦笑・汗 \"You probably haven’t talked directly to Minato much, right?\"\r\n苦笑・汗\r\n    「あまりミナトと、直接話したこともないですよね？」]])\r\nLAYER_LOAD_FACE(\"\")\r\n\r\n    LAYER_LOAD(50,\"BU_RIR07ca\")\r\n    SWITCH_SCREEN(\"mask000\",300,true)\r\n\r\nPLAY_VOICE(\"lira_0669.wav\")\r\n    MSG([[\r\n【Lira】\r\n驚き \"Uh, y-yeah...\"\r\n驚き\r\n    「ええっと、そ、そうだなー……」]])\r\n\r\n    LAYER_LOAD(50,\"BU_RIR07aa\")\r\n    SWITCH_SCREEN(\"mask000\",300,true)\r\n\r\nPLAY_VOICE(\"lira_0670.wav\")\r\n    MSG([[\r\n【Lira】\r\n通常 \"You know, Riko’s not cute at all, right? But Minato-kun treats her normally without any ulterior motives, and that kindness drew her in.\"\r\n通常 「リコってほら、全然顔が可愛くないじゃん？　それなのに、下心とか抜きで普通に接してくれるミナトくんの優しさに惹かれたんだよ」]])\r\n\r\n    LAYER_LOAD(50,\"BU_RIR07ga\")\r\n    SWITCH_SCREEN(\"mask000\",300,true)\r\n\r\nPLAY_VOICE(\"lira_0671.wav\")\r\n    MSG([[\r\n【Lira】\r\n焦り \"Ah! Of course that’s what Riko told me!? My memory’s fuzzy, so I’m not sure if it’s completely right! Haha!\"\r\n焦り\r\n    「あ！　も、もちろん今のはリコから聞いた話ね！？　アタシも記憶が曖昧で、正しいかわからないんだー！　あははは！」]])\r\n\r\nLAYER_LOAD_FACE(\"BU_ERI01ca\")\r\nPLAY_VOICE(\"erika_1389.wav\")\r\n    MSG([[\r\n【Erika】\r\n驚き \"Minato’s kindness?\"\r\n驚き\r\n    「ミナトの、優しさに」]])\r\nLAYER_LOAD_FACE(\"\")\r\n\r\n    LAYER_LOAD(50,\"\")\r\n    LAYER_LOAD(LAYER_BG,\"BG000ab\")\r\n    SWITCH_SCREEN(\"mask000\",1000,false)\r\n\r\n    -- //BG：駅前\r\n    FILTER_SCREEN(2)\r\n    LAYER_LOAD(LAYER_BG, \"BG002aa\")\r\n    -- //effect：セピア加工\r\n    -- //BU：リコ（ウインク）\r\n    LAYER_LOAD(50,\"BU_RIK01ia\")\r\n    SWITCH_SCREEN(\"mask035\" , 1000,false)\r\n\r\n    MSG([[I recalled the first time I met Riko-san.\r\nリコさんと初めて出会った時のことを思い出す。]])\r\n\r\n    MSG([[On entrance exam day, I happened to rescue Riko-san, who was protecting a girl being surrounded by a group of men in front of the station.\r\n入試の日に、駅前で男性の集団に囲まれていた女の子をかばっていたリコさんを、ボクは偶然助けることとなった。]])\r\n\r\n    MSG([[Honestly, I just acted naturally given the situation.\r\n正直に言って、その場の状況で自然とそうなっただけで。]])\r\n\r\n    MSG([[Unlike Riko-san, who actively helped the girl involved.\r\nリコさんみたいに、能動的に誰かを助けたワケじゃない。]])\r\n\r\n    MSG([[To me, Riko-san, who saved the girl being harassed, seemed like a much kinder person.\r\n絡まれていた女の子を助けたリコさんの方が、ボクにはずっと優しいヒトに思える。]])\r\n\r\nLAYER_LOAD_FACE(\"BU_ERI01fc\")\r\nPLAY_VOICE(\"erika_1390.wav\")\r\n    MSG([[\r\n【Erika】\r\n苦笑 (But... I’m glad she thought that much of my actions.)\r\n苦笑\r\n    （でも……ボクのあの行動をそこまで思ってもらえるなんて、嬉しいな）]])\r\n\r\nPLAY_VOICE(\"erika_1391.wav\")\r\n    MSG([[\r\n【Erika】\r\n苦笑 \"Even someone like me... can be liked by someone.\"\r\n苦笑\r\n    「こんなボクでも……誰かに好きになってもらえるんだ」]])\r\nLAYER_LOAD_FACE(\"\")\r\n\r\n    LAYER_LOAD(50,\"\")\r\n    LAYER_LOAD(LAYER_BG,\"BG000ab\")\r\n    FILTER_SCREEN(0)\r\n    SWITCH_SCREEN(\"mask035\",1000,false)\r\n\r\n    -- //BG：1-A教室（夕方）\r\n    LAYER_LOAD(LAYER_BG, \"BG014ba\")\r\n    -- //BU：リラ（驚き）\r\n    LAYER_LOAD(50,\"BU_RIR07ca\")\r\n    SWITCH_SCREEN(\"mask000\" , 1000,false)\r\n\r\nPLAY_VOICE(\"lira_0672.wav\")\r\n    MSG([[\r\n【Lira】\r\n驚き \"Erika...?\"\r\n驚き\r\n    「エリカ……？」]])\r\n\r\nLAYER_LOAD_FACE(\"BU_ERI01ca\")\r\nPLAY_VOICE(\"erika_1392.wav\")\r\n    MSG([[\r\n【Erika】\r\n焦り \"Ah! S-Sorry! Of course I’ll help! I’m sure Minato will be really happy when he knows Riko has feelings for him.\"\r\n焦り\r\n    「あ！　ご、ごめんなさい！　もちろんお手伝いしますよ！　ミナトもきっと、リコさんに想われていると知ったら、スゴく喜ぶと思います」]])\r\nLAYER_LOAD_FACE(\"\")\r\n\r\n    LAYER_LOAD(50,\"BU_RIR07ha\")\r\n    SWITCH_SCREEN(\"mask000\",300,true)\r\n\r\nPLAY_VOICE(\"lira_0673.wav\")\r\n    MSG([[\r\n【Lira】\r\n赤面 \"R-Really... haha.\"\r\n赤面\r\n    「そ、そう、かな……へへ」]])\r\n\r\nLAYER_LOAD_FACE(\"BU_ERI01ea\")\r\nPLAY_VOICE(\"erika_1393.wav\")\r\n    MSG([[\r\n【Erika】\r\n笑顔 \"So, how can I help? Please tell me anything.\"\r\n笑顔\r\n    「それで、私にどんなお手伝いができますか？　何でも言ってください」]])\r\nLAYER_LOAD_FACE(\"\")\r\n\r\nPLAY_VOICE(\"lira_0674.wav\")\r\n    MSG([[\r\n【Lira】\r\n赤面 \"Could we go on a date as the three of us this weekend? Riko would find going one-on-one too difficult at first.\"\r\n赤面\r\n    「今週末、エリカも交えて三人でデートできない？　最初から二人きりっていうのは、リコもハードル高いと思うし」]])\r\n\r\nLAYER_LOAD_FACE(\"BU_ERI01ca\")\r\nPLAY_VOICE(\"erika_1394.wav\")\r\n    MSG([[\r\n【Erika】\r\n驚き \"Th-Three people? Minato would be fine with that, but I, um, already have plans...\"\r\n驚き\r\n    「さ、三人ですか？　ミナトは平気だと思うんですけど、私はその、予定がありまして……」]])\r\nLAYER_LOAD_FACE(\"\")\r\n\r\n    LAYER_LOAD(50,\"BU_RIR07ga\")\r\n    SWITCH_SCREEN(\"mask000\",300,true)\r\n\r\nPLAY_VOICE(\"lira_0675.wav\")\r\n    MSG([[\r\n【Lira】\r\n焦り \"I-I see. Actually, I also have something to do, so I can’t join. What a pain... Minato probably wouldn’t want a one-on-one date, right?\"\r\n焦り 「そ、そっか。実はアタシも用事が入ってて参加できないんだよね。まいったな……ミナトくん、流石に二人きりでデートは嫌がるよね？」]])\r\n\r\nLAYER_LOAD_FACE(\"BU_ERI01ea\")\r\nPLAY_VOICE(\"erika_1395.wav\")\r\n    MSG([[\r\n【Erika】\r\n笑顔 \"That’s not true, he’d be thrilled.\"\r\n笑顔\r\n    「そんなことないですよ、大喜びです」]])\r\nLAYER_LOAD_FACE(\"\")\r\n\r\n    LAYER_LOAD(50,\"BU_RIR07ca\")\r\n    SWITCH_SCREEN(\"mask000\",300,true)\r\n\r\nPLAY_VOICE(\"lira_0676.wav\")\r\n    MSG([[\r\n【Lira】\r\n驚き \"You spoke confidently there.\"\r\n驚き\r\n    「言い切ったね」]])\r\n\r\n    MSG([[—Damn it! It’s my own matter, but talking about it like it’s someone else’s causes problems! It’s complicated!\r\n――しまった！\r\n    　自分のことなのに、自分のことのように話すと問題が起きるから難しい！]])\r\n\r\nLAYER_LOAD_FACE(\"BU_ERI01ga\")\r\nPLAY_VOICE(\"erika_1396.wav\")\r\n    MSG([[\r\n【Erika】\r\n焦り \"I- I just think so. Minato spends his weekends cooking or gaming.\"\r\n焦り\r\n    「そ、そう思うってだけです。ミナト、土日はいつも料理かゲームで潰してますから！」]])\r\nLAYER_LOAD_FACE(\"\")\r\n\r\n    LAYER_LOAD(50,\"BU_RIR07fc\")\r\n    SWITCH_SCREEN(\"mask000\",300,true)\r\n\r\nPLAY_VOICE(\"lira_0677.wav\")\r\n    MSG([[\r\n【Lira】\r\n苦笑 \"Well, that’s good. Sorry to ask, but can you tell Minato and ask him to keep that time free?\"\r\n苦笑\r\n    「それならいいんだけどさ。それじゃあ悪いけど、ミナトくんに伝えて、予定を押さえてもらっていいかな？」]])\r\n\r\n    LAYER_LOAD(50,\"BU_RIR07aa\")\r\n    SWITCH_SCREEN(\"mask000\",300,true)\r\n\r\nPLAY_VOICE(\"lira_0678.wav\")\r\n    MSG([[\r\n【Lira】\r\n通常 \"I’m sure after that, Riko will contact him directly on RINE.\"\r\n通常\r\n    「きっとあとはリコがＲＩＮＥで直接連絡をとっちゃうと思うから」]])\r\n\r\nLAYER_LOAD_FACE(\"BU_ERI01ea\")\r\nPLAY_VOICE(\"erika_1397.wav\")\r\n    MSG([[\r\n【Erika】\r\n笑顔 \"Understood. I’ll make sure to inform Minato responsibly.\"\r\n笑顔\r\n    「わかりました。責任をもってミナトに伝えておきますね」]])\r\nLAYER_LOAD_FACE(\"\")\r\n\r\n    LAYER_LOAD(50,\"BU_RIR07ea\")\r\n    SWITCH_SCREEN(\"mask000\",500,true)\r\n\r\nPLAY_VOICE(\"lira_0679.wav\")\r\n    MSG([[\r\n【Lira】\r\n笑顔 \"Thanks, Erika! I’ll tell Riko myself then. Bye-bye<sprite=\"Emoji\" name=\"star\">\"\r\n笑顔\r\n    「ありがとう、エリカ！　それじゃあ、リコにはアタシから言っておくね。バイビー<sprite=\"Emoji\" name=\"star\">」]])\r\n\r\n    -- //BU：なし\r\n    SWITCH_SCREEN(\"mask000\",0,false)\r\n    LAYER_MOVE_ALPHA(50,0,500,Ease.InSine)\r\n    LAYER_MOVE_POSITION(50,200,0,500,Ease.InSine)\r\n    WAIT(500)\r\n    LAYER_LOAD(50,\"\")\r\n\r\n    MSG([[After saying that, Lira-san left the classroom.\r\nそれだけ言うと、リラさんは教室を去っていった。]])\r\n\r\nLAYER_LOAD_FACE(\"BU_ERI01ea\")\r\nPLAY_VOICE(\"erika_1398.wav\")\r\n    MSG([[\r\n【Erika】\r\n笑顔 \"……………………\"\r\n笑顔\r\n    「……………………」]])\r\n\r\nLAYER_LOAD_FACE(\"BU_ERI01ha\")\r\nPLAY_VOICE(\"erika_1399.wav\")\r\n    MSG([[\r\n【Erika】\r\n赤面 \"Riko-san... likes me...\"\r\n赤面\r\n    「リコさんが……ボクを好き……」]])\r\nLAYER_LOAD_FACE(\"\")\r\n\r\n    MSG([[Alone, I replayed the conversation with Lira-san and felt a strange mix of happiness and embarrassment rise up, nearly making me make a weird noise.\r\n一人になったボクは、リラさんとの会話を反芻し、込み上げてくる嬉しさと恥ずかしさに変な声が出そうになった。]])\r\n\r\n    MSG([[I never imagined that the real me would ever be liked by a girl.\r\nまさか、素顔のボクが女の子から好意を向けられる日がくるなんて。]])\r\n\r\n    MSG([[My heart raced wildly with this first experience, my body burning hot as if it would melt away from the heat.\r\n初めての経験に胸がドキドキと高鳴って、カァッとカラダが熱くなって、そのまま熱で溶けちゃいそうだった。]])\r\n\r\nLAYER_LOAD_FACE(\"BU_ERI01ha\")\r\nPLAY_VOICE(\"erika_1400.wav\")\r\n    MSG([[\r\n【Erika】\r\n赤面 \"C-Calm down... The weekend date is important, but first, I need to talk to Hermes-san tomorrow.\"\r\n赤面\r\n    「お、落ち着こう……週末のデートも大事だけど、まずは明日、エルメスさんに話を聞かないといけないんだから」]])\r\nLAYER_LOAD_FACE(\"\")\r\n\r\n    MSG([[I forced my racing heart to calm down, for the time being.\r\nボクはひとまず、高ぶる心臓を無理やりに落ち着かせた。]])\r\n\r\n    MSG([[Just before Marika-nee fell ill this March, Hermes-san defeated her in the Princess Election and took the Princess title.\r\n今年の三月にマリカ姉さんが倒れる直前、エルメスさんは姉さんに姫皇選挙で勝利し、姫皇の称号を奪取していたんだ。]])\r\n\r\n    MSG([[The person who now holds the biggest clue to saving Marika-nee must be Hermes-san.\r\nマリカ姉さんを救うための手がかりを今最も握っているのは、エルメスさんに違いない。]])\r\n\r\n    MSG([[No matter what, I must get answers from Hermes-san—\r\n何があろうとも、エルメスさんから話を聞きださないと――]])\r\n\r\n    -- //BG：駅前\r\n    FILTER_SCREEN(2)\r\n    LAYER_LOAD(LAYER_BG, \"BG002aa\")\r\n    -- //effect：セピア加工\r\n    -- //BU：リコ（ウインク）\r\n    LAYER_LOAD(50,\"BU_RIK01ia\")\r\n    SWITCH_SCREEN(\"mask000\" , 1000,false)\r\n\r\nLAYER_LOAD_FACE(\"BU_ERI01ha\")\r\nPLAY_VOICE(\"erika_1401.wav\")\r\n    MSG([[\r\n【Erika】\r\n赤面 \"............\"\r\n赤面\r\n    「…………」]])\r\nLAYER_LOAD_FACE(\"\")\r\n\r\n    LAYER_LOAD(50,\"\")\r\n\r\n    -- //BG：1-A教室（夕方）\r\n    LAYER_LOAD(LAYER_BG, \"BG014ba\")\r\n    FILTER_SCREEN(0)\r\n    SWITCH_SCREEN(\"mask000\" , 500,false)\r\n\r\nLAYER_LOAD_FACE(\"BU_ERI01da\")\r\nPLAY_VOICE(\"erika_1402.wav\")\r\n    MSG([[\r\n【Erika】\r\n悲しみ \"—Hah! Idiot, idiot, I’m such an idiot! Focus more, focus! I have to save Marika-nee...\"\r\n悲しみ\r\n    「――はっ！　バカバカ、ボクのバカ！　もっと集中しろ、集中！　ボクはマリカ姉さんを救わないといけないんだから……」]])\r\nLAYER_LOAD_FACE(\"\")\r\n\r\n    MSG([[Until I save Marika-nee, there’s no time for love.\r\nマリカ姉さんを救うまで、恋愛なんてしてる場合じゃない。]])\r\n\r\n    MSG([[Even though I know that clearly, I can’t help but smile at the thought of someone liking me.\r\nわかり切っているはずなのに、つい自分に好意を向けてくれるヒトの存在が嬉しくて、頬が緩んでしまう。]])\r\n\r\n    MSG([[That made me feel pathetic beyond words.\r\nそんな自分が、情けなくて仕方なかった。]])\r\n\r\n    -- 　　　　◆\r\nSTOP_BGM(1000)\r\n    LAYER_LOAD(LAYER_BG, \"BG000aa\")\r\n    SWITCH_SCREEN(\"mask000\", 1000,false)\r\n    WAIT_INPUT(1000)\r\n\r\n    ScenarioManager.Next(\"RIR_EP04_05\")\r\nend\r\n"
}