{
  "m_GameObject": {
    "m_FileID": 0,
    "m_PathID": 0
  },
  "m_Enabled": 1,
  "m_Script": {
    "m_FileID": 0,
    "m_PathID": -1707786903170945384
  },
  "m_Name": "EP01_05",
  "Path": "Assets/AddressableAssets/Lua/Scenario/EP01/EP01_05.lua",
  "Text": "function EP01_05()\r\n    -- .承-2「疑惑と焦燥」\r\n    SaveData.Title = \"疑惑と焦燥\"\r\n\r\n    -- //BG：病室\r\n    LAYER_LOAD(LAYER_BG, \"BG009aa\")\r\n    SWITCH_SCREEN(\"mask000\" , 1000,false)\r\n\r\nPLAY_BGM(\"BGM09.wav\",0)\r\n\r\n    MSG([[\r\n    　懐かしい夢から目覚めると、変わらぬ現実が広がっていた。\r\n    　壁も床も真っ白な清潔感のある病室。殺菌用のアルコールと、ほのかな花の微香。\r\n    ]])\r\n\r\n    -- //CI：眠り続けるマリカ。 005\r\nLAYER_LOAD(50,\"CI005a\")\r\nLAYER_POSITION(50,0,-200)\r\nLAYER_MOVE_POSITION(50,0,0,500,Ease.OutSine)\r\nSWITCH_SCREEN(\"mask000\",500,false)\r\n\r\n    MSG([[\r\n    　そして、ベッドで眠り続けるマリカ姉さん。\r\n    ]])\r\n\r\nLAYER_LOAD_FACE(\"BU_MIN03da\")\r\nPLAY_VOICE(\"minato_0059.wav\")\r\n    MSG([[\r\n    【ミナト】私服・悲しみ\r\n    「……やっぱり、現実の出来事なんだね」\r\n    ]])\r\nLAYER_LOAD_FACE(\"\")\r\n\r\nLAYER_LOAD(50,\"\")\r\nSWITCH_SCREEN(\"mask000\",500,false)\r\n\r\n    MSG([[\r\n    　どうやら看病を続けている内に眠ってしまったらしい。\r\n    　看病に夢中で気付かなかったものの、そう言えば、丸一日以上も寝ていなかった。\r\n    ]])\r\n\r\n    MSG([[\r\n    　……いや、寝ている心の余裕がなかった、というのが正しいと思う。\r\n    ]])\r\n\r\n    MSG([[\r\n    　ハンバーガー屋で連絡を受けてから丸一日。\r\n    　主治医の先生や母さんから説明を受けたけれど、未だに信じられない。\r\n    ]])\r\n\r\n    MSG([[\r\n    　こんなにも元気そうで、肌の色も、ツヤもいい姉さんが、もう二度と目覚めない可能性があるだなんて。\r\n    ]])\r\n\r\nLAYER_LOAD_FACE(\"BU_MIN03da\")\r\nPLAY_VOICE(\"minato_0060.wav\")\r\n    MSG([[\r\n    【ミナト】悲しみ\r\n    「百合愛学園で、姉さんの身に何があったっていうの……？」\r\n    ]])\r\nLAYER_LOAD_FACE(\"\")\r\n\r\n    MSG([[\r\n    　昨日の主治医の先生と母さんのやり取りは、今でも脳裏に焼きついている。\r\n    ]])\r\n\r\n    -- //effect：セピア加工\r\nFILTER_SCREEN(2)\r\nSWITCH_SCREEN(\"mask009\" , 1000)\r\n\r\n    -- //BU：モブ医者、モブ女性\r\n    LAYER_LOAD(50,\"BU_MOB02aa\")\r\n    LAYER_POSITION(50,-400,0)\r\n    LAYER_LOAD(55,\"BU_MOB14aa\")\r\n    LAYER_POSITION(55,400,0)\r\n    SWITCH_SCREEN(\"mask000\",500,true)\r\n\r\nPLAY_VOICE(\"mother_0001.wav\")\r\n    MSG([[\r\n    【母さん】\r\n    「<r=びょうどういん>平等院</r>くん、遠慮は無用よ。早くマリカの容態について教えて」\r\n    ]])\r\n\r\nPLAY_VOICE(\"doctor_0001.wav\")\r\n    MSG([[\r\n    【主治医】\r\n    「お子さんの前ですが、よろしいのですか？　よければ、日を改めることもできますが」\r\n    ]])\r\n\r\nPLAY_VOICE(\"mother_0002.wav\")\r\n    MSG([[\r\n    【母さん】\r\n    「結論の先延ばしが嫌いなこと、よく知っているでしょう？　ミナトだってもう義務教育は終えた年齢よ、知っておくべきだわ」\r\n    ]])\r\n\r\nPLAY_VOICE(\"doctor_0002.wav\")\r\n    MSG([[\r\n    【主治医】\r\n    「……わかりました。ならば率直に申し上げます」\r\n    ]])\r\n\r\nPLAY_VOICE(\"doctor_0003.wav\")\r\n    MSG([[\r\n    【主治医】\r\n    「三日前の深夜に、私立百合愛学園から運ばれてきた際の外傷はすべて治療が完了しました」\r\n    ]])\r\n\r\nPLAY_VOICE(\"doctor_0004.wav\")\r\n    MSG([[\r\n    【主治医】\r\n    「頭部の傷が塞がるまで、様子を診なければなりませんが、既にいつ目覚めても不思議はない状態です」\r\n    ]])\r\n\r\nLAYER_LOAD_FACE(\"BU_MIN03ea\")\r\nPLAY_VOICE(\"minato_0061.wav\")\r\n    MSG([[\r\n    【ミナト】私服・笑顔\r\n    「ほ、本当ですか！？　じゃあマリカ姉さんは、じきに目覚めるんですね！」\r\n    ]])\r\nLAYER_LOAD_FACE(\"\")\r\n\r\nPLAY_VOICE(\"mother_0003.wav\")\r\n    MSG([[\r\n    【母さん】\r\n    「落ち着きなさい。子どもの前だからって曖昧な説明はやめて、平等院くん。アナタ、それでも医者なの？」\r\n    ]])\r\n\r\nPLAY_VOICE(\"mother_0004.wav\")\r\n    MSG([[\r\n    【母さん】\r\n    「マリカは目覚めるの？　目覚めないの？　結論を教えて」\r\n    ]])\r\n\r\nPLAY_VOICE(\"doctor_0005.wav\")\r\n    MSG([[\r\n    【主治医】\r\n    「心苦しいのですが……ハッキリとしたことは申し上げられないのが正直なところです」\r\n    ]])\r\n\r\nLAYER_LOAD_FACE(\"BU_MIN03ca\")\r\nPLAY_VOICE(\"minato_0062.wav\")\r\n    MSG([[\r\n    【ミナト】私服・驚き\r\n    「……え？」\r\n    ]])\r\n\r\nLAYER_LOAD_FACE(\"BU_MIN03ca\")\r\nPLAY_VOICE(\"minato_0063.wav\")\r\n    MSG([[\r\n    【ミナト】私服・驚き\r\n    「治療は、完了したんですよね……？　ど、どうして断言できないんですか？」\r\n    ]])\r\nLAYER_LOAD_FACE(\"\")\r\n\r\nPLAY_VOICE(\"doctor_0006.wav\")\r\n    MSG([[\r\n    【主治医】\r\n    「ええ、治療は完了しました。人工呼吸器すら必要がなく、身体的にはいつ目覚めても不思議ではない状態です」\r\n    ]])\r\n\r\nPLAY_VOICE(\"doctor_0007.wav\")\r\n    MSG([[\r\n    【主治医】\r\n    「にも関わらず、未だに昏睡状態が続いている。これは過去に例のない症状です。私たち医療チームの間でも意見が分かれており、原因の究明に努めています」\r\n    ]])\r\n\r\nPLAY_VOICE(\"mother_0005.wav\")\r\n    MSG([[\r\n    【母さん】\r\n    「まどろっこしいわね。つまり、何故かはわからないけれど、いつまで経っても目覚めないってことでしょ？」\r\n    ]])\r\n\r\nPLAY_VOICE(\"doctor_0008.wav\")\r\n    MSG([[\r\n    【主治医】\r\n    「おっしゃる通り……いつ目覚めるかについては断言できかねます」\r\n    ]])\r\n\r\nLAYER_LOAD_FACE(\"BU_MIN03da\")\r\nPLAY_VOICE(\"minato_0064.wav\")\r\n    MSG([[\r\n    【ミナト】私服・悲しみ\r\n    「そ、それじゃあマリカ姉さんはどうなるんですか……！？　このまま、ずっと眠ったままなんですか！？」\r\n    ]])\r\nLAYER_LOAD_FACE(\"\")\r\n\r\nPLAY_VOICE(\"doctor_0009.wav\")\r\n    MSG([[\r\n    【主治医】\r\n    「残念ながら、現時点では何とも……。身体的には何ら問題は見られませんので、しばらく経過を診ていきたいと考えています」\r\n    ]])\r\n\r\nPLAY_VOICE(\"mother_0006.wav\")\r\n    MSG([[\r\n    【母さん】\r\n    「経過を診る、ね……期待できないわ。このまま回復せずに、『植物状態』に陥ることも覚悟しておくわ」\r\n    ]])\r\n\r\nLAYER_LOAD_FACE(\"BU_MIN03ga\")\r\nPLAY_VOICE(\"minato_0065.wav\")\r\n    MSG([[\r\n    【ミナト】私服・焦り\r\n    「しょ、植物状態……！？　マリカ姉さんが……！？」\r\n    ]])\r\n\r\nPLAY_VOICE(\"minato_0066.wav\")\r\n    MSG([[\r\n    【ミナト】私服・焦り\r\n    「どうにもならないんですか！？　マリカ姉さんのために、ボクにできることはないんですか！？」\r\n    ]])\r\nLAYER_LOAD_FACE(\"\")\r\n\r\nPLAY_VOICE(\"doctor_0010.wav\")\r\n    MSG([[\r\n    【主治医】\r\n    「…………」\r\n    ]])\r\n\r\nPLAY_VOICE(\"mother_0007.wav\")\r\n    MSG([[\r\n    【母さん】\r\n    「先生から離れなさい、ミナト。ごめんなさいね。その子、マリカのことになると熱くなりすぎるのよ」\r\n    ]])\r\n\r\nPLAY_VOICE(\"doctor_0011.wav\")\r\n    MSG([[\r\n    【主治医】\r\n    「いえ……混乱するのも当然でしょう。私たち医療チームも、マリカさんの回復のために最善を尽くす心づもりです」\r\n    ]])\r\n\r\nPLAY_VOICE(\"doctor_0012.wav\")\r\n    MSG([[\r\n    【主治医】\r\n    「今後の治療では、自宅療養と当院での入院、二つから選択いただけます」\r\n    ]])\r\n\r\nPLAY_VOICE(\"doctor_0013.wav\")\r\n    MSG([[\r\n    【主治医】\r\n    「自宅療養では入院費用がかからず、自宅でいつでも容態を確認いただけるので安心でしょう」\r\n    ]])\r\n\r\nPLAY_VOICE(\"doctor_0014.wav\")\r\n    MSG([[\r\n    【主治医】\r\n    「ただマリカさんの場合、過去に例の少ない症状ですので、不測の事態が起こりかねません。自宅療養では、有事の際の対応が遅れてしまうというリスクがあります」\r\n    ]])\r\n\r\nPLAY_VOICE(\"doctor_0015.wav\")\r\n    MSG([[\r\n    【主治医】\r\n    「当院での入院の場合、入院費用が最大の懸念点でしょう。もし入院を希望されるのでしたら、保険の適用外の費用については一部を当院で負担いたしましょう」\r\n    ]])\r\n\r\nPLAY_VOICE(\"mother_0008.wav\")\r\n    MSG([[\r\n    【母さん】\r\n    「長期入院の費用を負担する？　やけに親切なのね。まるで、入院を選んでもらわなきゃ都合が悪いみたいじゃない」\r\n    ]])\r\n\r\nPLAY_VOICE(\"mother_0009.wav\")\r\n    MSG([[\r\n    【母さん】\r\n    「一体、どこからの指示なのかしらね」\r\n    ]])\r\n\r\nPLAY_VOICE(\"doctor_0016.wav\")\r\n    MSG([[\r\n    【主治医】\r\n    「……他意はありません。私たちもマリカさんが目覚められるよう、前向きな治療を続ける方針だというだけです」\r\n    ]])\r\n\r\nPLAY_VOICE(\"mother_0010.wav\")\r\n    MSG([[\r\n    【母さん】\r\n    「……まぁいいわ。どうせウチには、自宅療養を続ける余裕はないもの。費用面の問題さえ解決してもらえるなら、入院を希望するわ」\r\n    ]])\r\n\r\nPLAY_VOICE(\"doctor_0017.wav\")\r\n    MSG([[\r\n    【主治医】\r\n    「では、細かな手続きはまた後日に」\r\n    ]])\r\n\r\nLAYER_LOAD_FACE(\"BU_MIN03ba\")\r\nPLAY_VOICE(\"minato_0067.wav\")\r\n    MSG([[\r\n    【ミナト】私服・真剣\r\n    「お、教えてください……マリカ姉さんの身に、何が起きたんですか？一体、深夜の学園で何をしていたんですか！？　誰が病院まで運んでくださったんですか！？」\r\n    ]])\r\nLAYER_LOAD_FACE(\"\")\r\n\r\nPLAY_VOICE(\"mother_0011.wav\")\r\n    MSG([[\r\n    【母さん】\r\n    「やめなさい、ミナト。平等院くんにわかるワケがないし、仮に知っていたとしても、立場上話せないわ」\r\n    ]])\r\n\r\nPLAY_VOICE(\"doctor_0018.wav\")\r\n    MSG([[\r\n    【主治医】\r\n    「……すみません。伊草さんの言った通りです。ただひとつだけ、医者としての立場を抜きに個人的な見解を述べさせていただきます」\r\n    ]])\r\n\r\nPLAY_VOICE(\"doctor_0019.wav\")\r\n    MSG([[\r\n    【主治医】\r\n    「肉体的には健康そのもののマリカさんに、目覚めない理由があるとすれば、精神的な要因でしょう」\r\n    ]])\r\n\r\nPLAY_VOICE(\"doctor_0020.wav\")\r\n    MSG([[\r\n    【主治医】\r\n    「医学的には説明がつかずとも、感情がヒトの生死に関わった例はいくらでも存在します」\r\n    ]])\r\n\r\nPLAY_VOICE(\"doctor_0021.wav\")\r\n    MSG([[\r\n    【主治医】\r\n    「ご家族の皆さんが望みを捨てず、前向きに接し続ければ、事態は好転していくはずです」\r\n    ]])\r\n\r\n    MSG([[\r\n    　主治医の先生が与えてくれたささやかな希望さえ、その時のボクにはとても耳に入らなかった。\r\n    ]])\r\n\r\n    FILTER_SCREEN(0)\r\n    LAYER_LOAD(50,\"\")\r\n    LAYER_LOAD(55,\"\")\r\n    LAYER_LOAD(LAYER_BG,\"BG000aa\")\r\n    SWITCH_SCREEN(\"mask000\",2000,false)\r\n    WAIT_INPUT(1000)\r\n\r\n    -- //effect：セピア加工・終了\r\n--FILTER_SCREEN(0)\r\n--SWITCH_SCREEN(\"mask009\" , 1000,false)\r\n\r\n    MSG([[\r\n    　そして、現在に至る。\r\n    ]])\r\n\r\n    -- //BG：病室（夕方）\r\n    LAYER_LOAD(LAYER_BG, \"BG009ba\")\r\n    SWITCH_SCREEN(\"mask000\" , 1000,false)\r\n    WAIT_INPUT(1000)\r\n\r\n    -- //BG：病室（夜）\r\n    LAYER_LOAD(LAYER_BG, \"BG009ca\")\r\n    SWITCH_SCREEN(\"mask000\" , 1000,false)\r\n    WAIT_INPUT(1000)\r\n\r\n    -- //SE： 引き戸の開閉音\r\n    PLAY_SE(\"SEb004.wav\")\r\n    WAIT(500)\r\n\r\n    -- //BU：モブ女性\r\n    LAYER_LOAD(50,\"BU_MOB02aa\")\r\n    LAYER_POSITION(50,100,0)\r\n    LAYER_MOVE_POSITION(50,0,0,500,Ease.OutSine)\r\n    SWITCH_SCREEN(\"mask000\",500,true)\r\n\r\n    MSG([[\r\n    　病室の扉が開き、母さんが入ってきた。\r\n    ]])\r\n\r\nPLAY_VOICE(\"mother_0012.wav\")\r\n    MSG([[\r\n    【母さん】\r\n    「まだ帰っていなかったのね、ミナト。\r\n    　早く家に帰って休みなさい。ただでさえ、受験勉強でクタクタでしょう？」\r\n    ]])\r\n\r\n    MSG([[\r\n    　ボクの顔を見て、酷く面倒臭いモノでも見るように、深いタメ息をつく母さん。\r\n    ]])\r\n\r\n    MSG([[\r\n    　バリバリのキャリアウーマンで効率を何より重視する母さんは昔から、要領の悪いボクに対して、失望の表情を見せることが多かった。\r\n    ]])\r\n\r\n    MSG([[\r\n    　きっと今も、ボクではなく姉さんが倒れたことに落胆しているのだろう。\r\n    ]])\r\n\r\nLAYER_LOAD_FACE(\"BU_MIN03aa\")\r\nPLAY_VOICE(\"minato_0068.wav\")\r\n    MSG([[\r\n    【ミナト】私服・通常\r\n    「まだ、姉さんのそばにいたいんだよ。ほら、本当にたまにだけど、ボクの声に反応してくれるから、もしかしたらボクに気付いているのかも、って……」\r\n    ]])\r\nLAYER_LOAD_FACE(\"\")\r\n\r\nPLAY_VOICE(\"mother_0013.wav\")\r\n    MSG([[\r\n    【母さん】\r\n    「医者の話を聞いていなかったの？　それは身体が反射的に動いているだけよ。ちゃんと意識中枢が機能しているなら、目を覚ますはずだわ」\r\n    ]])\r\n\r\n    MSG([[\r\n    　ボクの言葉を無情にも一蹴し、母さんは続ける。\r\n    ]])\r\n\r\nPLAY_VOICE(\"mother_0014.wav\")\r\n    MSG([[\r\n    【母さん】\r\n    「まぁ声は聞こえているらしいけれどね」\r\n    ]])\r\n\r\nPLAY_VOICE(\"mother_0015.wav\")\r\n    MSG([[\r\n    【母さん】\r\n    「ただ、目覚めない原因は、精神的な問題かもしれないという話だし、その詳細が分からないことには、解決のしようがないわ。今は諦めなさい」\r\n    ]])\r\n\r\nLAYER_LOAD_FACE(\"BU_MIN03ga\")\r\nPLAY_VOICE(\"minato_0069.wav\")\r\n    MSG([[\r\n    【ミナト】私服・焦り\r\n    「原因……そ、そうだ！　百合愛学園は！？\r\n    　姉さんが見つかった学園なら、何か知っているはずでしょ！？」\r\n    ]])\r\nLAYER_LOAD_FACE(\"\")\r\n\r\n    MSG([[\r\n    　母さんは疲れ切った様子で首を横に振った。\r\n    ]])\r\n\r\nPLAY_VOICE(\"mother_0016.wav\")\r\n    MSG([[\r\n    【母さん】\r\n    「今日、百合愛学園の理事と話をしてきたけれど……ろくな話はできなかったわ。マリカは学園でも人気者で、悩んでいた様子もなく、原因はわからないの一点張り」\r\n    ]])\r\n\r\nPLAY_VOICE(\"mother_0017.wav\")\r\n    MSG([[\r\n    【母さん】\r\n    「挙げ句の果てに、治療費を負担するからこの件は内密にして欲しいとまで言ってきてね」\r\n    ]])\r\n\r\nPLAY_VOICE(\"mother_0018.wav\")\r\n    MSG([[\r\n    【母さん】\r\n    「まぁ私としても、娘をスキャンダルの渦中に入れたくはないから、受け入れたけれどね」\r\n    ]])\r\n\r\nLAYER_LOAD_FACE(\"BU_MIN03ba\")\r\nPLAY_VOICE(\"minato_0070.wav\")\r\n    MSG([[\r\n    【ミナト】私服・真剣\r\n    「え！？　か、母さんはそれでいいの！？\r\n    　姉さんの身にこんな酷いことが起きたのに、表沙汰にしなくても平気だっていうの！？」\r\n    ]])\r\nLAYER_LOAD_FACE(\"\")\r\n\r\nPLAY_VOICE(\"mother_0019.wav\")\r\n    MSG([[\r\n    【母さん】\r\n    「表沙汰にしたところで、事件性が薄いから悲劇の事故としてお茶の間を賑わせて終わりよ。それに、マリカを入院させ続けるお金だって、ウチにはないの」\r\n    ]])\r\n\r\nPLAY_VOICE(\"mother_0020.wav\")\r\n    MSG([[\r\n    【母さん】\r\n    「百合愛学園の提案に従うのが、誰も傷つかずに済む最善の選択肢なのよ。……悔しいけれどね」\r\n    ]])\r\n\r\n    MSG([[\r\n    　それまで冷静な表情であった母さんの顔に、苛立ちの色が滲む。\r\n    　見れば両の拳が、ギュッと強く握りしめられていた。\r\n    ]])\r\n\r\n    MSG([[\r\n    　ボクはバカだ。\r\n    　母さんだって、悔しいに決まってる。\r\n    ]])\r\n\r\n    MSG([[\r\n    　自分の娘がこんな目に遭って、悲しくない親なんているワケないじゃないか。\r\n    ]])\r\n\r\n    MSG([[\r\n    　ボクは母さんに謝って、言われた通り、自宅に帰って休むことを決めた。\r\n    ]])\r\n\r\n    LAYER_LOAD(50,\"\")\r\n    LAYER_LOAD(LAYER_BG,\"BG000aa\")\r\n    SWITCH_SCREEN(\"mask000\",2000,false)\r\n    WAIT_INPUT(1000)\r\n\r\n    -- //BG：病室（朝）\r\n    LAYER_LOAD(LAYER_BG, \"BG009aa\")\r\n    SWITCH_SCREEN(\"mask000\" , 2000,false)\r\n    WAIT_INPUT(1000)\r\n\r\n    -- //BG：病室（夜）\r\n    LAYER_LOAD(LAYER_BG, \"BG009ca\")\r\n    SWITCH_SCREEN(\"mask000\" , 2000,false)\r\n    WAIT_INPUT(1000)\r\n\r\n    MSG([[\r\n    　それから毎日、ボクは姉さんの病室に通った。\r\n    ]])\r\n\r\n    -- //BG：病室（朝）\r\n    LAYER_LOAD(LAYER_BG, \"BG009aa\")\r\n    SWITCH_SCREEN(\"mask000\" , 2000,false)\r\n    WAIT_INPUT(1000)\r\n\r\n    -- //BG：病室（夜）\r\n    LAYER_LOAD(LAYER_BG, \"\")\r\n    SWITCH_SCREEN(\"mask000\" , 2000,false)\r\n\r\n    MSG([[\r\n    　だけど、姉さんは目覚めなかった。\r\n    ]])\r\n\r\n    -- //BG：病室（朝）\r\n    LAYER_LOAD(LAYER_BG, \"BG009aa\")\r\n    SWITCH_SCREEN(\"mask000\" , 2000,false)\r\n    WAIT_INPUT(1000)\r\n\r\n    -- //BG：病室（夜）\r\n    LAYER_LOAD(LAYER_BG, \"BG009ca\")\r\n    SWITCH_SCREEN(\"mask000\" , 2000,false)\r\n\r\n    MSG([[\r\n    　いつまでも、目覚めなかった。\r\n    ]])\r\n\r\n    -- //BG：病室（朝）\r\n    LAYER_LOAD(LAYER_BG, \"BG009aa\")\r\n    SWITCH_SCREEN(\"mask000\" , 2000,false)\r\n\r\n    -- //BG：病室（夜）\r\n    LAYER_LOAD(LAYER_BG, \"BG009ca\")\r\n    SWITCH_SCREEN(\"mask000\" , 2000,false)\r\n\r\n    MSG([[\r\n    　いつまでも。\r\n    ]])\r\n\r\n    -- //BG：病室（朝）\r\n    LAYER_LOAD(LAYER_BG, \"BG009aa\")\r\n    SWITCH_SCREEN(\"mask000\" , 2000,false)\r\n\r\n    -- //BG：病室（夜）\r\n    LAYER_LOAD(LAYER_BG, \"BG009ca\")\r\n    SWITCH_SCREEN(\"mask000\" , 2000,false)\r\n\r\n    MSG([[\r\n    　いつまでも――\r\n    ]])\r\n\r\n    LAYER_LOAD(LAYER_BG,\"BG000aa\")\r\n    SWITCH_SCREEN(\"mask000\" , 1000)\r\n    WAIT_INPUT(1000)\r\n\r\n    -- //BG：病室（夕方）\r\n    LAYER_LOAD(LAYER_BG, \"BG009ba\")\r\n    SWITCH_SCREEN(\"mask000\" , 1000)\r\n\r\nLAYER_LOAD_FACE(\"BU_MIN03ea\")\r\nPLAY_VOICE(\"minato_0071.wav\")\r\n    MSG([[\r\n    【ミナト】私服・笑顔\r\n    「マリカ姉さん、見てよ！　やったんだよ！\r\n    　百合愛学園の男子部への、合格通知がきたんだ！」\r\n    ]])\r\nLAYER_LOAD_FACE(\"\")\r\n\r\n    MSG([[\r\n    　ボクは病室まで持参した百合愛学園の合格通知を姉さんの眠るベッドの脇に置き、得意気に鼻を鳴らした。\r\n    ]])\r\n\r\nLAYER_LOAD_FACE(\"BU_MIN03ea\")\r\nPLAY_VOICE(\"minato_0072.wav\")\r\n    MSG([[\r\n    【ミナト】私服・笑顔\r\n    「これで、姉さんと同じ学校に通えるんだよ！\r\n    　へへ。これでボクも、少しは姉さんに追いつけたかな？」\r\n    ]])\r\n\r\nLAYER_LOAD_FACE(\"BU_MIN03aa\")\r\nPLAY_VOICE(\"minato_0073.wav\")\r\n    MSG([[\r\n    【ミナト】私服・通常\r\n    「マリカ姉さん、ボク、昔より成長してるかな……？」\r\n    ]])\r\nLAYER_LOAD_FACE(\"\")\r\n\r\n    -- //CI：眠り続ける姉 005\r\nLAYER_LOAD(50,\"CI005a\")\r\nSWITCH_SCREEN(\"mask000\",500,false)\r\n\r\n    MSG([[\r\n    　マリカ姉さんから返事はない。\r\n    　目の前にいるのに、会えなかった頃よりもずっと、ずっと遠く離れた場所にいるみたいだ。\r\n    ]])\r\n\r\nLAYER_LOAD(50,\"\")\r\nSWITCH_SCREEN(\"mask000\",500,false)\r\n\r\nLAYER_LOAD_FACE(\"BU_MIN03da\")\r\nPLAY_VOICE(\"minato_0074.wav\")\r\n    MSG([[\r\n    【ミナト】私服・悲しみ\r\n    「ねえ、答えてよ……マリカ姉さん。\r\n    　ボク、ずっと姉さんに追いつきたくてがんばってきたのに……こんなのって、こんなのってないよ……」\r\n    ]])\r\nLAYER_LOAD_FACE(\"\")\r\n\r\n    MSG([[\r\n    　ダメだ。\r\n    　一度気持ちを口に出してしまうと、もう止められない。\r\n    ]])\r\n\r\n    MSG([[\r\n    　この数週間、ずっと喉元で抑え込んでいた感情が一気に湧き上がってきて、涙と一緒に溢れ出る。\r\n    ]])\r\n\r\nLAYER_LOAD_FACE(\"BU_MIN03da\")\r\nPLAY_VOICE(\"minato_0075.wav\")\r\n    MSG([[\r\n    【ミナト】私服・悲しみ\r\n    「またお話がしたいよ……笑ってる顔が見たいよ……目を覚ましてよ…！帰ってきてよ、マリカ姉さん！」\r\n    ]])\r\nLAYER_LOAD_FACE(\"\")\r\n\r\n    MSG([[\r\n    　思わず、マリカ姉さんの手を握りしめた。\r\n    ]])\r\n\r\n    MSG([[\r\n    　すると、その時――\r\n    ]])\r\n\r\n    -- //SE：鼓動\r\n    PLAY_SE(\"SEa025.wav\")\r\n    WAIT(500)\r\n\r\nLAYER_LOAD_FACE(\"BU_MIN03ca\")\r\nPLAY_VOICE(\"minato_0076.wav\")\r\n    MSG([[\r\n    【ミナト】私服・驚き\r\n    「えっ」\r\n    ]])\r\nLAYER_LOAD_FACE(\"\")\r\n\r\n    MSG([[\r\n    　ボクの手を、マリカ姉さんが握り返してくれた。\r\n    ]])\r\n\r\n    MSG([[\r\n    　きっとそれは無意識の反射運動。\r\n    　姉さんが自分の意志で、握り返したワケじゃない。\r\n    ]])\r\n\r\n    MSG([[\r\n    　だけどその温もりは、子どもの頃に家まで手を引いてくれた、あの頃のままで。\r\n    ]])\r\n\r\n    MSG([[\r\n    　数年ぶりに、ようやくマリカ姉さんと再会できたような心地となり、頬がゆるんで、泣きながら笑ってしまう。\r\n    ]])\r\n\r\nLAYER_LOAD_FACE(\"BU_MIN03ja\")\r\nPLAY_VOICE(\"minato_0077.wav\")\r\n    MSG([[\r\n    【ミナト】私服・泣き笑い\r\n    「ボクは、バカだなぁ」\r\n    ]])\r\nLAYER_LOAD_FACE(\"\")\r\n\r\n    MSG([[\r\n    　そうだ。大バカだ。\r\n    　一人で悩んで、勝手に絶望して、諦めて。\r\n    　マリカ姉さんに守られていた頃から、何も成長できていなかった。\r\n    ]])\r\n\r\n    MSG([[\r\n    　どのような形であっても、ボクの目の前に姉さんがいる事実は変わらない。\r\n    ]])\r\n\r\n    MSG([[\r\n    　なら、ボクがやるべきことはただひとつ――\r\n    ]])\r\n\r\n\r\nLAYER_LOAD_FACE(\"BU_MIN03ja\")\r\nPLAY_VOICE(\"minato_0078.wav\")\r\n    MSG([[\r\n    【ミナト】私服・泣き笑い\r\n    「マリカ姉さんは……まだ生きている。なら絶望する必要なんてまったくないじゃないか。\r\n    　ボクがこれから、姉さんを救っちゃえばいいんだから」\r\n    ]])\r\nLAYER_LOAD_FACE(\"\")\r\n\r\n    MSG([[\r\n    　そこで、ベッド上の合格通知書が視界に入り、入試の日に出会ったリコさんとの会話を思い出した。\r\n    ]])\r\n\r\n\r\n    -- //BG：ハンバーガー屋（セピア加工）\r\n    LAYER_LOAD(LAYER_BG, \"BG001aa\")\r\nFILTER_SCREEN(2)\r\n\r\n    -- //BU：素顔リラ（笑顔）\r\n    LAYER_LOAD(50,\"BU_RIK01ea\")\r\n    SWITCH_SCREEN(\"mask010\" , 1000,false)\r\n\r\nPLAY_VOICE(\"lira_0045.wav\")\r\n    MSG([[\r\n    【リコ】素顔リラ・笑顔\r\n    「百合学の高等部ではさ、学内で最高にカワイイ四人の生徒に『姫』の称号を与えて、生徒自身に自治をさせてるんだよ」\r\n    ]])\r\n\r\n    LAYER_LOAD(50,\"\")\r\n\r\n    -- //BG：病室（夕方）\r\n    LAYER_LOAD(LAYER_BG, \"BG009ba\")\r\n    FILTER_SCREEN(0)\r\n    SWITCH_SCREEN(\"mask009\" , 1000,false)\r\n\r\nLAYER_LOAD_FACE(\"BU_MIN03ca\")\r\nPLAY_VOICE(\"minato_0079.wav\")\r\n    MSG([[\r\n    【ミナト】私服・驚き\r\n    「そうだ……自治をしている『姫』ってヒトたちなら、マリカ姉さんのことだって何か知ってるかもしれない」\r\n    ]])\r\nLAYER_LOAD_FACE(\"\")\r\n\r\n    MSG([[\r\n    　中等部の生徒であるリコさんだって、姉さんを知っているような反応だった。\r\n    ]])\r\n\r\n    MSG([[\r\n    　『姫』と呼ばれるようなヒトたちなら、少なくとも、理事や教員よりも内情に詳しいことは間違いない。\r\n    ]])\r\n\r\n    MSG([[\r\n    　マリカ姉さんを目覚めさせる手がかりがあるとすれば、姉さんが意識不明で倒れていたという、私立百合愛学園しか考えれないんだ。\r\n    ]])\r\n\r\nLAYER_LOAD_FACE(\"BU_MIN03ba\")\r\nPLAY_VOICE(\"minato_0080.wav\")\r\n    MSG([[\r\n    【ミナト】私服・真剣\r\n    「決めたよ、マリカ姉さん。\r\n    　ボクは絶対に……姉さんの身に起こった事件の真相を暴き出してみせる！」\r\n    ]])\r\nLAYER_LOAD_FACE(\"\")\r\n\r\n    LAYER_LOAD(LAYER_BG,\"BG000aa\")\r\n    SWITCH_SCREEN(\"mask000\",1000,false)\r\n    WAIT_INPUT(1000)\r\n\r\n    -- //BG：病室（夜）\r\n    LAYER_LOAD(LAYER_BG, \"BG009ca\")\r\n\r\n    -- //BU：モブ女性\r\n    LAYER_LOAD(50,\"BU_MOB02aa\")\r\n    SWITCH_SCREEN(\"mask000\" , 1000)\r\n\r\n    MSG([[\r\n    　その日の夜、病室へやってきた母さんに、自分の考えを正直に話してみた。\r\n    ]])\r\n\r\n    MSG([[\r\n    　母さんはボクの話に理解は示しつつも、その顔に不安の色を滲ませて、ボクが調査を行うことに反対する。\r\n    ]])\r\n\r\nPLAY_VOICE(\"mother_0021.wav\")\r\n    MSG([[\r\n    【母さん】\r\n    「確かに、学園がマリカについて何かを隠したがっていることは間違いないわ。でも、イチ生徒の立場からその秘密を探ろうだなんて危険過ぎるわよ」\r\n    ]])\r\n\r\nPLAY_VOICE(\"mother_0022.wav\")\r\n    MSG([[\r\n    【母さん】\r\n    「学園はある意味で閉鎖的な場所。\r\n    　今回マリカについての情報を全然訊き出せなかったみたいに、いくらでも秘密は揉み消せてしまうの」\r\n    ]])\r\n\r\nPLAY_VOICE(\"mother_0023.wav\")\r\n    MSG([[\r\n    【母さん】\r\n    「もし学園側にミナトの考えが知られたら、あなた、どんな酷い目に遭うか分からないのよ？\r\n    　その危険を承知で言っているの？」\r\n    ]])\r\n\r\nLAYER_LOAD_FACE(\"BU_MIN03ba\")\r\nPLAY_VOICE(\"minato_0081.wav\")\r\n    MSG([[\r\n    【ミナト】私服・真剣\r\n    「危険は百も承知だよ。でも、手がかりは他にないんだ。\r\n    　ボクが必ず、姉さんが学校で倒れていた理由を突きとめてみせるよ！」\r\n    ]])\r\n\r\nPLAY_VOICE(\"minato_0082.wav\")\r\n    MSG([[\r\n    【ミナト】私服・真剣\r\n    「だからお願い。ボクの調査が終わるまでの間は、延命治療を続けるかどうかの判断は保留にしてよ！\r\n    　絶対に、姉さんを目覚めさせてみせるから！」\r\n    ]])\r\nLAYER_LOAD_FACE(\"\")\r\n\r\nPLAY_VOICE(\"mother_0024.wav\")\r\n    MSG([[\r\n    【母さん】\r\n    「はぁ～～～～～……」\r\n    ]])\r\n\r\n    MSG([[\r\n    　母さんがボクの目をじっと見つめて、今まで見てきた中で最も深いタメ息をついた。\r\n    ]])\r\n\r\nPLAY_VOICE(\"mother_0025.wav\")\r\n    MSG([[\r\n    【母さん】\r\n    「まったく……アナタもマリカも、言い出したら聞かないんだから。\r\n    　わかったわ。あなたの好きなようにやりなさい」\r\n    ]])\r\n\r\nPLAY_VOICE(\"mother_0026.wav\")\r\n    MSG([[\r\n    【母さん】\r\n    「ただし、一年後には結論を出すわよ。\r\n    　母さんも色々と調べてね、植物状態が一年以上続くと目覚める確率は更に低くなることがわかったの」\r\n    ]])\r\n\r\nPLAY_VOICE(\"mother_0027.wav\")\r\n    MSG([[\r\n    【母さん】\r\n    「それ以上結論を先延ばしにするのは、誰のためにもならないわ。\r\n    　私たちはもちろん……マリカ自身にもね」\r\n    ]])\r\n\r\nLAYER_LOAD_FACE(\"BU_MIN03ea\")\r\nPLAY_VOICE(\"minato_0083.wav\")\r\n    MSG([[\r\n    【ミナト】私服・笑顔\r\n    「……わかった。ありがとう、母さん。\r\n    　一年以内に、姉さんを絶対に救ってみせるよ！！」\r\n    ]])\r\nLAYER_LOAD_FACE(\"\")\r\n\r\n    LAYER_LOAD(50,\"\")\r\n    SWITCH_SCREEN(\"mask000\",500,true)\r\n\r\n    MSG([[\r\n    　こうして、ボクの四月からの新たな学園生活に、あまりにも責任重大な目的が生まれた。\r\n    ]])\r\n\r\n    MSG([[\r\n    　それは一年以内に、マリカ姉さんが目覚めない理由を突き止めること。\r\n    　私立百合愛学園には間違いなく、姉さんに関わる何か重大な秘密があるはずだ。\r\n    ]])\r\n\r\n    MSG([[\r\n    　ボクはそれを必ず暴き出す。\r\n    　たとえ、学園を敵に回すことになろうとも。\r\n    　どれほど過酷な運命が待ち受けていようとも、絶対に。\r\n    ]])\r\n\r\n    -- 　　　◆\r\nSTOP_BGM(1000)\r\nLAYER_LOAD_FACE(\"\")\r\n    LAYER_LOAD(LAYER_BG, \"\")\r\n    SWITCH_SCREEN(\"mask000\" , 1000)\r\n    WAIT_INPUT(1000)\r\n\r\n    ScenarioManager.Next(\"EP01_06\")\r\n\r\nend\r\n"
}