{
  "m_GameObject": {
    "m_FileID": 0,
    "m_PathID": 0
  },
  "m_Enabled": 1,
  "m_Script": {
    "m_FileID": 0,
    "m_PathID": -1707786903170945384
  },
  "m_Name": "EP05_14",
  "Path": "Assets/AddressableAssets/Lua/Scenario/EP05/ERI/EP05_14.lua",
  "Text": "function ERI_EP05_14()\r\n    --.転-6【2月第4週】「伊草ミナト、一世一代の大告白」\r\n    SaveData.Title = \"伊草ミナト、一世一代の大告白\"\r\n\r\n    --//BG：メインストリート（夏）\r\n    LAYER_LOAD(LAYER_BG, \"BG019aa\")\r\n    SWITCH_SCREEN(\"mask000\" , 1000,false)\r\n\r\nPLAY_BGM(\"BGM03.wav\")\r\n\r\n    MSG([[\r\n    　その後も慌ただしい日々が続いた。\r\n    ]])\r\n\r\n    MSG([[\r\n    　何と言ったって、競争相手はあの国民的アイドルの姫神エルメスさんだ。\r\n    ]])\r\n\r\n    MSG([[\r\n    　いくら女装がバレて広まった悪評を拭うことができたとしても、そもそも地力が違い過ぎる。\r\n    ]])\r\n\r\n    MSG([[\r\n    　少しでも日々のアピール活動を怠ると、すぐに差がついて大変だった。\r\n    ]])\r\n\r\n    LAYER_LOAD(LAYER_BG,\"BG000aa\")\r\n    SWITCH_SCREEN(\"mask000\",1000,false)\r\n    WAIT_INPUT(1000)\r\n\r\n    --//BG：アキラ宅\r\n    LAYER_LOAD(LAYER_BG, \"BG023aa\")\r\n    SWITCH_SCREEN(\"mask000\" , 1000,false)\r\n\r\nLAYER_LOAD_FACE(\"BU_MIN01aa\")\r\nPLAY_VOICE(\"minato_0888.wav\")\r\n    MSG([[\r\n    【ミナト】通常\r\n    「ただいまー」\r\n    ]])\r\nLAYER_LOAD_FACE(\"\")\r\n\r\n    LAYER_LOAD(50,\"BU_AKI03aa\")\r\n    SWITCH_SCREEN(\"mask000\",500,true)\r\n\r\nPLAY_VOICE(\"akira_0790.wav\")\r\n    MSG([[\r\n    【アキラ】通常・部屋着\r\n    「おかおかー、男子部の授業お疲れですよー」\r\n    ]])\r\n\r\nPLAY_VOICE(\"akira_0791.wav\")\r\n    MSG([[\r\n    【アキラ】通常・部屋着\r\n    「選挙期間中くらい男子部の授業は休んでしまえばいいのに、真面目ですねー」\r\n    ]])\r\n\r\nLAYER_LOAD_FACE(\"BU_MIN01fc\")\r\nPLAY_VOICE(\"minato_0889.wav\")\r\n    MSG([[\r\n    【ミナト】苦笑\r\n    「一ヶ月近くも休んじゃったもの。遅れを取り戻すのに精いっぱいだよ」\r\n    ]])\r\n\r\nLAYER_LOAD_FACE(\"BU_MIN01aa\")\r\nPLAY_VOICE(\"minato_0890.wav\")\r\n    MSG([[\r\n    【ミナト】通常\r\n    「それに、性別がバレてしまった以上、素顔の状態でも『姫』として振舞わないとね」\r\n    ]])\r\nLAYER_LOAD_FACE(\"\")\r\n\r\n    LAYER_LOAD(50,\"BU_AKI03fa\")\r\n    SWITCH_SCREEN(\"mask000\",300,true)\r\n\r\nPLAY_VOICE(\"akira_0792.wav\")\r\n    MSG([[\r\n    【アキラ】苦笑・汗・部屋着\r\n    「あー……それもそうですね。お気の毒に」\r\n    ]])\r\n\r\n    --//SE：LINEっぽいの\r\nPLAY_SE(\"SEb019.wav\")\r\nWAIT(500)\r\n\r\n    LAYER_LOAD(50,\"BU_AKI03ga\")\r\n    SWITCH_SCREEN(\"mask000\",300,true)\r\n\r\nPLAY_VOICE(\"akira_0793.wav\")\r\n    MSG([[\r\n    【アキラ】焦り・汗・部屋着\r\n    「うげっ…」\r\n    ]])\r\n\r\nLAYER_LOAD_FACE(\"BU_MIN01aa\")\r\nPLAY_VOICE(\"minato_0891.wav\")\r\n    MSG([[\r\n    【ミナト】通常\r\n    「スマホ鳴ったよ。大丈夫なの？」\r\n    ]])\r\nLAYER_LOAD_FACE(\"\")\r\n\r\n    LAYER_LOAD(50,\"BU_AKI03da\")\r\n    SWITCH_SCREEN(\"mask000\",300,true)\r\n\r\nPLAY_VOICE(\"akira_0794.wav\")\r\n    MSG([[\r\n    【アキラ】悲しみ・部屋着\r\n    「無視します。どうせヒユさん辺りからの相談です」\r\n    ]])\r\n\r\nPLAY_VOICE(\"akira_0795.wav\")\r\n    MSG([[\r\n    【アキラ】悲しみ・部屋着\r\n    「最近、何を思ったのか、アナタの騎士たちからやたらと相談をされるんですよね。学園に来て欲しいとかも言われて、うんざりです」\r\n    ]])\r\n\r\nLAYER_LOAD_FACE(\"BU_MIN01ea\")\r\nPLAY_VOICE(\"minato_0892.wav\")\r\n    MSG([[\r\n    【ミナト】笑顔\r\n    「えー、いいことじゃない」\r\n    ]])\r\n\r\nPLAY_VOICE(\"minato_0893.wav\")\r\n    MSG([[\r\n    【ミナト】笑顔\r\n    「みんな、アキラを頼ってくれてるってことだよ」\r\n    ]])\r\nLAYER_LOAD_FACE(\"\")\r\n\r\nPLAY_VOICE(\"akira_0796.wav\")\r\n    MSG([[\r\n    【アキラ】悲しみ・部屋着\r\n    「それが負担なんですよねー……期待なんかされたって何もお返しできないのに」\r\n    ]])\r\n\r\n--;吉　テキスト修正「暮らしていたい」→「暮らしていきたい」(2020/02/02 23:51）\r\nPLAY_VOICE(\"akira_0797.wav\")\r\n    MSG([[\r\n    【アキラ】悲しみ・部屋着\r\n    「何の期待も背負わずに、ゲームだけして暮らしていきたいんですよ、私は」\r\n    ]])\r\n\r\nLAYER_LOAD_FACE(\"BU_MIN01fa\")\r\nPLAY_VOICE(\"minato_0894.wav\")\r\n    MSG([[\r\n    【ミナト】苦笑・汗\r\n    「あはは。それは、難しいんじゃないかな？　実況者として暮らすのも、動画編集とかネタ探しとか大変なんでしょ？」\r\n    ]])\r\nLAYER_LOAD_FACE(\"\")\r\n\r\n    LAYER_LOAD(50,\"BU_AKI03aa\")\r\nPLAY_VOICE(\"akira_0798.wav\")\r\n    MSG([[\r\n    【アキラ】通常・部屋着\r\n    「まぁそうなんですけどね」\r\n    ]])\r\n\r\n    MSG([[\r\n    　アキラの言いたいことはスゴくわかる。\r\n    　誰かに期待されるのって、嬉しいことではあるけれど、負担でもあるんだ。\r\n    ]])\r\n\r\n    MSG([[\r\n    　期待に応えようと、ついついがんばり過ぎてしまうから。\r\n    ]])\r\n\r\nLAYER_LOAD_FACE(\"BU_MIN01ea\")\r\nPLAY_VOICE(\"minato_0895.wav\")\r\n    MSG([[\r\n    【ミナト】笑顔\r\n    「でも、悪い気分じゃないんでしょ？　アキラは元々、おばさんたちの期待に応えるために勉強をがんばってたもんね」\r\n    ]])\r\n\r\nLAYER_LOAD_FACE(\"BU_MIN01aa\")\r\nPLAY_VOICE(\"minato_0896.wav\")\r\n    MSG([[\r\n    【ミナト】通常\r\n    「アキラが実はスッゴくがんばり屋さんだって、ボクは知ってるよ」\r\n    ]])\r\nLAYER_LOAD_FACE(\"\")\r\n\r\n    LAYER_LOAD(50,\"BU_AKI03ha\")\r\n    SWITCH_SCREEN(\"mask000\",300,true)\r\n\r\nPLAY_VOICE(\"akira_0799.wav\")\r\n    MSG([[\r\n    【アキラ】赤面・部屋着\r\n    「……ありがとう、ございます。まぁ実際、悪い気分じゃ、ないですよ」\r\n    ]])\r\n\r\nPLAY_VOICE(\"akira_0800.wav\")\r\n    MSG([[\r\n    【アキラ】赤面・部屋着\r\n    「ミナちんのためなら……私、少しはがんばってもいいかなって思うんです」\r\n    ]])\r\n\r\nLAYER_LOAD_FACE(\"BU_MIN01fa\")\r\nPLAY_VOICE(\"minato_0897.wav\")\r\n    MSG([[\r\n    【ミナト】苦笑・汗\r\n    「ボクなんかよりも、自分のためにがんばってあげて欲しいなぁ」\r\n    ]])\r\nLAYER_LOAD_FACE(\"\")\r\n\r\nPLAY_VOICE(\"akira_0801.wav\")\r\n    MSG([[\r\n    【アキラ】赤面・部屋着\r\n    「だ、だってそれはぁ……」\r\n    ]])\r\n\r\n    MSG([[\r\n    　そこで言葉を止めて、アキラは「ぐぬぬ」とうなった。\r\n    ]])\r\n\r\n    MSG([[\r\n    　それから冷蔵庫に向かって、テーブルからラップのかかった料理をテーブルに並べていく。\r\n    ]])\r\n\r\n    LAYER_LOAD(50,\"BU_AKI03aa\")\r\n    SWITCH_SCREEN(\"mask000\",300,true)\r\n\r\nPLAY_VOICE(\"akira_0802.wav\")\r\n    MSG([[\r\n    【アキラ】通常・部屋着\r\n    「と、ともかく、まずはご飯にしましょう。今日は私が当番なので、ミナちん特製のオムライスに挑戦してみたんですよ」\r\n    ]])\r\n\r\nLAYER_LOAD_FACE(\"BU_MIN01ea\")\r\nPLAY_VOICE(\"minato_0898.wav\")\r\n    MSG([[\r\n    【ミナト】笑顔\r\n    「え、もしかしてオムライス作ったの？　スゴいよアキラ！」\r\n    ]])\r\nLAYER_LOAD_FACE(\"\")\r\n\r\n    LAYER_LOAD(50,\"BU_AKI03da\")\r\n    SWITCH_SCREEN(\"mask000\",300,true)\r\n\r\nPLAY_VOICE(\"akira_0803.wav\")\r\n    MSG([[\r\n    【アキラ】悲しみ・部屋着\r\n    「あ、いえ」\r\n    ]])\r\n\r\n    MSG([[\r\n    　テーブルに並んでいくのは、焦げた玉子焼きがたくさん乗った皿。\r\n    ]])\r\n\r\n    MSG([[\r\n    　そっか。\r\n    　上手く焼けずに苦戦しちゃったんだ。\r\n    ]])\r\n\r\nPLAY_VOICE(\"akira_0804.wav\")\r\n    MSG([[\r\n    【アキラ】悲しみ・部屋着\r\n    「今日のところは、オムレツライスで勘弁してください…」\r\n    ]])\r\n\r\nLAYER_LOAD_FACE(\"BU_MIN01ea\")\r\nPLAY_VOICE(\"minato_0899.wav\")\r\n    MSG([[\r\n    【ミナト】笑顔\r\n    「うんうん、最初はこうなるよね。ボクも最初はいっぱい失敗したなー」\r\n    ]])\r\nLAYER_LOAD_FACE(\"\")\r\n\r\nPLAY_VOICE(\"akira_0805.wav\")\r\n    MSG([[\r\n    【アキラ】悲しみ・部屋着\r\n    「ううぅ……いっそ叱ってくださいよ。玉子をいっぱい無駄にしちゃったんですし」\r\n    ]])\r\n\r\nLAYER_LOAD_FACE(\"BU_MIN01ea\")\r\nPLAY_VOICE(\"minato_0900.wav\")\r\n    MSG([[\r\n    【ミナト】笑顔\r\n    「何を言ってるの？　全然無駄になんかならないよ」\r\n    ]])\r\nLAYER_LOAD_FACE(\"\")\r\n\r\n    MSG([[\r\n    　へこんだ様子のアキラの頭を撫でて、ボクは冷蔵庫へと向かう。\r\n    ]])\r\n\r\nLAYER_LOAD_FACE(\"BU_MIN01ea\")\r\nPLAY_VOICE(\"minato_0901.wav\")\r\n    MSG([[\r\n    【ミナト】笑顔\r\n    「ケチャップ以外にもスパイス入りのお塩とか、チリソースや大根おろしソースも用意して、玉子焼きパーティーにしよう」\r\n    ]])\r\n\r\nLAYER_LOAD_FACE(\"BU_MIN01aa\")\r\nPLAY_VOICE(\"minato_0902.wav\")\r\n    MSG([[\r\n    【ミナト】通常\r\n    「ボクだって料理に関しては、アキラと同じくらい素敵な作戦を思いつけるからね」\r\n    ]])\r\nLAYER_LOAD_FACE(\"\")\r\n\r\n    LAYER_LOAD(50,\"BU_AKI03eb\")\r\n    SWITCH_SCREEN(\"mask000\",300,true)\r\n\r\nPLAY_VOICE(\"akira_0806.wav\")\r\n    MSG([[\r\n    【アキラ】笑顔・部屋着\r\n    「ミナちん…」\r\n    ]])\r\n\r\n    LAYER_LOAD(50,\"BU_AKI03ga\")\r\n    SWITCH_SCREEN(\"mask000\",300,true)\r\n\r\nPLAY_VOICE(\"akira_0807.wav\")\r\n    MSG([[\r\n    【アキラ】焦り・部屋着\r\n    「あ！　私もソース作り手伝うので、少しだけ待っててください」\r\n    ]])\r\n\r\n    MSG([[\r\n    　アキラはそう言うと、先ほど手に取らなかったスマホを手に取って、素早く操作を始めた。\r\n    ]])\r\n\r\nLAYER_LOAD_FACE(\"BU_MIN01aa\")\r\nPLAY_VOICE(\"minato_0903.wav\")\r\n    MSG([[\r\n    【ミナト】通常\r\n    「どうしたの？」\r\n    ]])\r\nLAYER_LOAD_FACE(\"\")\r\n\r\n    LAYER_LOAD(50,\"BU_AKI03ga\")\r\n    SWITCH_SCREEN(\"mask000\",300,true)\r\n\r\nPLAY_VOICE(\"akira_0808.wav\")\r\n    MSG([[\r\n    【アキラ】焦り・汗・部屋着\r\n    「い、いや……やっぱり、私宛のメッセージにはちゃんと返しておこうかな、って」\r\n    ]])\r\n\r\n    LAYER_LOAD(50,\"BU_AKI03da\")\r\n    SWITCH_SCREEN(\"mask000\",300,true)\r\n\r\nPLAY_VOICE(\"akira_0809.wav\")\r\n    MSG([[\r\n    【アキラ】悲しみ・部屋着\r\n    「玉子焼きを作り過ぎてしまった時には自己嫌悪で死にたくなりましたけど、今ミナちんが素敵にフォローしてくれたでしょう？」\r\n    ]])\r\n\r\n    LAYER_LOAD(50,\"BU_AKI03fd\")\r\n    SWITCH_SCREEN(\"mask000\",300,true)\r\n\r\nPLAY_VOICE(\"akira_0810.wav\")\r\n    MSG([[\r\n    【アキラ】苦笑・部屋着\r\n    「失敗したって誰かが助けてくれるでしょうし、別に期待に応えられなくたって死にはしないですし、肩のチカラを抜いて対応しようと思ったんです」\r\n    ]])\r\n\r\nLAYER_LOAD_FACE(\"BU_MIN01fc\")\r\nPLAY_VOICE(\"minato_0904.wav\")\r\n    MSG([[\r\n    【ミナト】苦笑\r\n    「うんうん。期待に潰されちゃうくらいなら、そっちの方がいいと思うよ」\r\n    ]])\r\n\r\nLAYER_LOAD_FACE(\"BU_MIN01da\")\r\nPLAY_VOICE(\"minato_0905.wav\")\r\n    MSG([[\r\n    【ミナト】悲しみ\r\n    「ボクも百合愛学園での生活の中で何度も苦しんだし、きっとマリカ姉さんも同じだったと思う」\r\n    ]])\r\n\r\nPLAY_VOICE(\"minato_0906.wav\")\r\n    MSG([[\r\n    【ミナト】悲しみ\r\n    「……難しいよね。肩のチカラを抜いて、素の自分でいることって」\r\n    ]])\r\nLAYER_LOAD_FACE(\"\")\r\n\r\n    MSG([[\r\n    　アキラの発案で女装を始めてからこの一年間。\r\n    ]])\r\n\r\n    MSG([[\r\n    　女装して『姫』となって。『姫』として、多くの期待を背負って。その期待を裏切って、素の自分を曝け出されて。\r\n    ]])\r\n\r\n    MSG([[\r\n    　そして多くのヒトに受け入れてもらった。\r\n    ]])\r\n\r\n    MSG([[\r\n    　そんなボクだからこそ、理解者を得ることの難しさはよく知っている。\r\n    ]])\r\n\r\nLAYER_LOAD_FACE(\"BU_MIN01aa\")\r\nPLAY_VOICE(\"minato_0907.wav\")\r\n    MSG([[\r\n    【ミナト】通常\r\n    （本当に、たくさんのことがあった一年間だったなぁ）\r\n    ]])\r\nLAYER_LOAD_FACE(\"\")\r\n\r\n    MSG([[\r\n    　それも、もうすぐ区切りがつく。\r\n    　マリカ姉さんを救うためのタイムリミットはもう間近。\r\n    ]])\r\n\r\n    MSG([[\r\n    　今度の姫皇選挙が今度こそ、正真正銘、伊草エリカとしての最終決戦だ。\r\n    ]])\r\n\r\nLAYER_LOAD_FACE(\"BU_MIN01aa\")\r\nPLAY_VOICE(\"minato_0908.wav\")\r\n    MSG([[\r\n    【ミナト】通常\r\n    （今のこの生活も……終わるんだね）\r\n    ]])\r\nLAYER_LOAD_FACE(\"\")\r\n\r\n    MSG([[\r\n    　そう思うと、どうしてもひとつだけ心残りがある。\r\n    　その心残りを解消するために、ボクはアキラにひとつお願いをしてみることにした。\r\n    ]])\r\n\r\nLAYER_LOAD_FACE(\"BU_MIN01aa\")\r\nPLAY_VOICE(\"minato_0909.wav\")\r\n    MSG([[\r\n    【ミナト】通常\r\n    「ねえアキラ。ご飯を食べ終わったら、ひとつお願いがあるんだけど」\r\n    ]])\r\nLAYER_LOAD_FACE(\"\")\r\n\r\n    LAYER_LOAD(50,\"BU_AKI03aa\")\r\n    SWITCH_SCREEN(\"mask000\",300,true)\r\n\r\nPLAY_VOICE(\"akira_0811.wav\")\r\n    MSG([[\r\n    【アキラ】通常・部屋着\r\n    「何ですか？　珍しいですね、ミナちんからお願いなんて」\r\n    ]])\r\n\r\nLAYER_LOAD_FACE(\"BU_MIN01aa\")\r\nPLAY_VOICE(\"minato_0910.wav\")\r\n    MSG([[\r\n    【ミナト】通常\r\n    「うん、実はね……」\r\n    ]])\r\n\r\nLAYER_LOAD_FACE(\"BU_MIN01ea\")\r\nPLAY_VOICE(\"minato_0911.wav\")\r\n    MSG([[\r\n    【ミナト】笑顔\r\n    「ボクと一緒に寝て欲しいんだ」\r\n    ]])\r\nLAYER_LOAD_FACE(\"\")\r\n\r\nPLAY_VOICE(\"akira_0812.wav\")\r\n    MSG([[\r\n    【アキラ】通常・部屋着\r\n    「はいはい、一緒に寝ればいいんですねー」\r\n    ]])\r\n\r\n    LAYER_LOAD(50,\"BU_AKI03ha\")\r\n    SWITCH_SCREEN(\"mask000\",500,true)\r\n\r\nPLAY_VOICE(\"akira_0813.wav\")\r\n    MSG([[\r\n    【アキラ】赤面・部屋着\r\n    「……は！？」\r\n    ]])\r\n\r\n    LAYER_LOAD(50,\"\")\r\nSTOP_BGM(1000)\r\n\r\n    --　　　　　◆\r\n    LAYER_LOAD(LAYER_BG, \"BG000aa\")\r\n    SWITCH_SCREEN(\"mask000\" , 1000,false)\r\n    WAIT_INPUT(1000)\r\n\r\n    --//CG：アキラと添い寝（赤面）\r\n    LAYER_LOAD(LAYER_BG, \"EV048ad\")\r\n    SWITCH_SCREEN(\"mask007\" , 1000,false)\r\n\r\nPLAY_BGM(\"BGM08.wav\",2000,true)\r\n\r\nPLAY_VOICE(\"akira_0814.wav\")\r\n    MSG([[\r\n    【アキラ】\r\n    「な、何で今更、添い寝の訓練なんかぁ……」\r\n    ]])\r\n\r\n    MSG([[\r\n    　ひとつのベッドに並んで寝そべって数秒。\r\n    　さっそく限界を迎えた様子で、アキラが震え声で弱音を漏らした。\r\n    ]])\r\n\r\nPLAY_VOICE(\"minato_0912.wav\")\r\n    MSG([[\r\n    【ミナト】\r\n    「な、何だか、改めてやると恥ずかしいね」\r\n    ]])\r\n\r\nPLAY_VOICE(\"akira_0815.wav\")\r\n    MSG([[\r\n    【アキラ】\r\n    「アナタが言い出しっぺでしょ…！？　責任をとってくださいよ、この空気」\r\n    ]])\r\n\r\nPLAY_VOICE(\"minato_0913.wav\")\r\n    MSG([[\r\n    【ミナト】\r\n    「ええ……でも最初にこの訓練をした時、アキラは『従兄妹同士で恥ずかしがる必要ない』って言ってたじゃない」\r\n    ]])\r\n\r\nPLAY_VOICE(\"akira_0816.wav\")\r\n    MSG([[\r\n    【アキラ】\r\n    「それは、そうですけどぉ……うう、顔が熱い……死んじゃいそうです」\r\n    ]])\r\n\r\n    MSG([[\r\n    　アキラにはそう言ったものの、ボクも何だか身体が熱い。\r\n    ]])\r\n\r\n    MSG([[\r\n    　以前の緊張から来る火照りとは、微妙に違う。\r\n    　何だか、胸が静かにトクトクと脈打って、少し切なくて。\r\n    ]])\r\n\r\n    MSG([[\r\n    　もっとアキラとの距離を縮めたくなるような、不思議な心地がする。\r\n    ]])\r\n\r\n    MSG([[\r\n    　だけれど決して、イヤな気分ではなかった。\r\n    ]])\r\n\r\nPLAY_VOICE(\"minato_0914.wav\")\r\n    MSG([[\r\n    【ミナト】\r\n    「変なことを言い出してごめんね、アキラ。この暮らしも、きっともうすぐ終わるから……今のうちにって思ったんだ」\r\n    ]])\r\n\r\nPLAY_VOICE(\"akira_0817.wav\")\r\n    MSG([[\r\n    【アキラ】\r\n    「そっか……そう、ですよね」\r\n    ]])\r\n\r\n    --//CG：アキラと添い寝（悲しみ）\r\n    LAYER_LOAD(LAYER_BG, \"EV048ae\")\r\n    SWITCH_SCREEN(\"mask000\" , 500,false)\r\n\r\nPLAY_VOICE(\"akira_0818.wav\")\r\n    MSG([[\r\n    【アキラ】\r\n    「次の姫皇選挙で勝つにしても、負けるにしても。マリっちょを救うことができたとしても、できなくても、終わるんですよね」\r\n    ]])\r\n\r\nPLAY_VOICE(\"akira_0819.wav\")\r\n    MSG([[\r\n    【アキラ】\r\n    「私たちの、『ボク姫ＰＲＯＪＥＣＴ』は」\r\n    ]])\r\n\r\n    MSG([[\r\n    　アキラの手がボクの方へと伸びて、そっと指を絡ませる。\r\n    ]])\r\n\r\nPLAY_VOICE(\"minato_0915.wav\")\r\n    MSG([[\r\n    【ミナト】\r\n    「うん、だからね……アキラには、どうしても伝えておきたかったんだよ」\r\n    ]])\r\n\r\n    MSG([[\r\n    　その手を握り返して、微笑みかけた。\r\n    ]])\r\n\r\n    --//CG：アキラと添い寝（赤面）\r\n    LAYER_LOAD(LAYER_BG, \"EV048ad\")\r\n    SWITCH_SCREEN(\"mask000\" , 500,false)\r\n\r\n    MSG([[\r\n    　すると、アキラの顔から悲しみの色がさっと失われた。\r\n    ]])\r\n\r\nPLAY_VOICE(\"akira_0820.wav\")\r\n    MSG([[\r\n    【アキラ】\r\n    「へ……？」\r\n    ]])\r\n\r\nPLAY_VOICE(\"minato_0916.wav\")\r\n    MSG([[\r\n    【ミナト】\r\n    「ずーっと隠してた、ボクの本当の気持ちを」\r\n    ]])\r\n\r\nPLAY_VOICE(\"akira_0821.wav\")\r\n    MSG([[\r\n    【アキラ】\r\n    「は、はい……」\r\n    ]])\r\n\r\nPLAY_VOICE(\"minato_0917.wav\")\r\n    MSG([[\r\n    【ミナト】\r\n    「アキラ、ボクはね」\r\n    ]])\r\n\r\n    MSG([[\r\n    　今にも破裂しそうな胸に手を当てる。\r\n    　アキラの目を真っすぐに見つめ、乱れた呼吸を落ち着かせる。\r\n    ]])\r\n\r\n    MSG([[\r\n    　そしてボクの胸の内がしっかりと伝わるように、想いを言葉にした。\r\n    ]])\r\n\r\nPLAY_VOICE(\"minato_0918.wav\")\r\n    MSG([[\r\n    【ミナト】\r\n    「アキラと一緒に、百合愛学園に通いたいんだ」\r\n    ]])\r\n\r\nPLAY_VOICE(\"akira_0822.wav\")\r\n    MSG([[\r\n    【アキラ】\r\n    「………………へ？」\r\n    ]])\r\n\r\n    MSG([[\r\n    　あれ？\r\n    　ボクの一世一代の告白に対して、アキラからは予想外の気の抜けた言葉が返ってきた。\r\n    ]])\r\n\r\n    MSG([[\r\n    　もしかしたら、聞こえづらかったのかもしれない。\r\n    　恥ずかしいけれど、もう一度、ちゃんと自分の気持ちを言葉にしよう。\r\n    ]])\r\n\r\nPLAY_VOICE(\"minato_0919.wav\")\r\n    MSG([[\r\n    【ミナト】\r\n    「アキラと一緒に百合愛学園に通いたいんだよ。マリカ姉さんを救えた、そのあとに」\r\n    ]])\r\n\r\nPLAY_VOICE(\"akira_0823.wav\")\r\n    MSG([[\r\n    【アキラ】\r\n    「一緒に通いたい、って……？　はい？」\r\n    ]])\r\n\r\nPLAY_VOICE(\"minato_0920.wav\")\r\n    MSG([[\r\n    【ミナト】\r\n    「だ、だからね、今まではアキラにがんばらなくていいって言ってきたけど、本当は一緒に登校したかったんだよ」\r\n    ]])\r\n\r\nPLAY_VOICE(\"minato_0921.wav\")\r\n    MSG([[\r\n    【ミナト】\r\n    「い、イヤな気分にさせちゃったらごめんね。でもボク、アキラが大好きだから、大好きなアキラとこれからも一緒にいたいから、だから……」\r\n    ]])\r\n\r\nPLAY_VOICE(\"akira_0824.wav\")\r\n    MSG([[\r\n    【アキラ】\r\n    「――それは嬉しいんですけど！」\r\n    ]])\r\n\r\nSTOP_BGM(1000)\r\n\r\n    MSG([[\r\n    　アキラはボクの言葉を遮るように声を張り上げた。\r\n    ]])\r\n    --//CI：ベッドで悶えるゆるアキラ 109\r\n\r\n    MSG([[\r\n    　そしてなんとベッドの上を勢いよく転がり始めた！\r\n    ]])\r\n\r\nPLAY_BGM(\"BGM07.wav\")\r\n\r\nPLAY_VOICE(\"akira_0825.wav\")\r\n    MSG([[\r\n    【アキラ】\r\n    「喜んで一緒に通いますけど！　けど！　今の空気で言うのは違うでしょ…！　違うでしょーーーーーー！」\r\n    ]])\r\n\r\nPLAY_VOICE(\"akira_0826.wav\")\r\n    MSG([[\r\n    【アキラ】\r\n    「んんんもおおおおおおおおおおおお！！！！」\r\n    ]])\r\n\r\nPLAY_VOICE(\"minato_0922.wav\")\r\n    MSG([[\r\n    【ミナト】\r\n    「アキラ！？　どうしちゃったの！？　シーツがぐちゃぐちゃになるから、そんなことしちゃダメだよ！？」\r\n    ]])\r\n\r\nPLAY_VOICE(\"akira_0827.wav\")\r\n    MSG([[\r\n    【アキラ】\r\n    「ぐちゃぐちゃなのは私の乙女心ですよーーーーーーーーーーーーーーー！！！！！！」\r\n    ]])\r\n\r\n    MSG([[\r\n    　暴れ回るアキラを宥めつつ、ボクはアキラから「一緒に学園に通ってもいい」と言ってもらえたことを嬉しく思った。\r\n    ]])\r\n\r\n    MSG([[\r\n    　エルメスさんに勝って、マリカ姉さんを救ったあとも、アキラと一緒の時間を過ごせる。\r\n    ]])\r\n\r\n    MSG([[\r\n    　そう思うだけで、今まで以上にチカラが湧いてくるんだ。\r\n    ]])\r\n\r\nPLAY_VOICE(\"minato_0923.wav\")\r\n    MSG([[\r\n    【ミナト】\r\n    （今はまだアキラは、ボクのことを仲のいい従兄だと思ってくれているだろうけど）\r\n    ]])\r\n\r\nPLAY_VOICE(\"minato_0924.wav\")\r\n    MSG([[\r\n    【ミナト】\r\n    （この先もずっと一緒にいられたら、もしかしたら――）\r\n    ]])\r\n\r\n    MSG([[\r\n    　流石に、まだこの本心を明かす勇気はない。\r\n    　今は、アキラと一緒に過ごせる時間が伸びるだけで満足だった。\r\n    ]])\r\n\r\n    MSG([[\r\n    　そしてボクたちは遂に、姫皇選挙の当日を迎える――\r\n    ]])\r\n\r\n    --　　　　　◆\r\nSTOP_BGM(1000)\r\n    LAYER_LOAD(LAYER_BG, \"BG000aa\")\r\n    SWITCH_SCREEN(\"mask000\" , 1000,false)\r\n    WAIT_INPUT(1000)\r\n\r\n    ScenarioManager.Next(\"ERI_EP05_15\")\r\nend\r\n"
}